{
"meta":{"test_sets":[],"test_metrics":[],"learn_metrics":[{"best_value":"Min","name":"RMSE"}],"launch_mode":"Train","parameters":"","iteration_count":1000,"learn_sets":["learn"],"name":"experiment"},
"iterations":[
{"learn":[14.59871775],"iteration":0,"passed_time":0.143465799,"remaining_time":143.3223332},
{"learn":[14.22518863],"iteration":1,"passed_time":0.145394121,"remaining_time":72.55166637},
{"learn":[13.8866124],"iteration":2,"passed_time":0.1466823695,"remaining_time":48.74744079},
{"learn":[13.52356875],"iteration":3,"passed_time":0.1479196149,"remaining_time":36.8319841},
{"learn":[13.18870211],"iteration":4,"passed_time":0.1514339983,"remaining_time":30.13536566},
{"learn":[12.9124226],"iteration":5,"passed_time":0.1529649969,"remaining_time":25.34120115},
{"learn":[12.60003351],"iteration":6,"passed_time":0.1541644601,"remaining_time":21.86932983},
{"learn":[12.32990573],"iteration":7,"passed_time":0.155204939,"remaining_time":19.24541244},
{"learn":[12.0660619],"iteration":8,"passed_time":0.1564912236,"remaining_time":17.23142251},
{"learn":[11.77309809],"iteration":9,"passed_time":0.1576000853,"remaining_time":15.60240845},
{"learn":[11.49227636],"iteration":10,"passed_time":0.1586939572,"remaining_time":14.26802942},
{"learn":[11.26264833],"iteration":11,"passed_time":0.1598021265,"remaining_time":13.15704175},
{"learn":[11.04260393],"iteration":12,"passed_time":0.161434067,"remaining_time":12.25657109},
{"learn":[10.79916926],"iteration":13,"passed_time":0.1632946361,"remaining_time":11.50060794},
{"learn":[10.5541002],"iteration":14,"passed_time":0.1647363549,"remaining_time":10.8176873},
{"learn":[10.31918115],"iteration":15,"passed_time":0.166232588,"remaining_time":10.22330416},
{"learn":[10.10004441],"iteration":16,"passed_time":0.1677626548,"remaining_time":9.700628805},
{"learn":[9.894556723],"iteration":17,"passed_time":0.1690496928,"remaining_time":9.222599908},
{"learn":[9.690174082],"iteration":18,"passed_time":0.1700004608,"remaining_time":8.777392215},
{"learn":[9.506034866],"iteration":19,"passed_time":0.1711824063,"remaining_time":8.387937907},
{"learn":[9.338524633],"iteration":20,"passed_time":0.1722687922,"remaining_time":8.031007026},
{"learn":[9.170203312],"iteration":21,"passed_time":0.1732967293,"remaining_time":7.703827329},
{"learn":[9.010299969],"iteration":22,"passed_time":0.1746621445,"remaining_time":7.419344138},
{"learn":[8.843866678],"iteration":23,"passed_time":0.1760582383,"remaining_time":7.159701692},
{"learn":[8.690548059],"iteration":24,"passed_time":0.1776940484,"remaining_time":6.930067886},
{"learn":[8.555307687],"iteration":25,"passed_time":0.178999685,"remaining_time":6.705603584},
{"learn":[8.413851302],"iteration":26,"passed_time":0.1802837095,"remaining_time":6.496890717},
{"learn":[8.29256019],"iteration":27,"passed_time":0.1819607137,"remaining_time":6.316636204},
{"learn":[8.162193833],"iteration":28,"passed_time":0.1831354789,"remaining_time":6.131881034},
{"learn":[8.040736294],"iteration":29,"passed_time":0.1841989934,"remaining_time":5.955767454},
{"learn":[7.921220278],"iteration":30,"passed_time":0.1853510282,"remaining_time":5.793714399},
{"learn":[7.809589039],"iteration":31,"passed_time":0.1865585826,"remaining_time":5.643397125},
{"learn":[7.699675801],"iteration":32,"passed_time":0.1878092193,"remaining_time":5.503379244},
{"learn":[7.60645267],"iteration":33,"passed_time":0.1888723581,"remaining_time":5.366196998},
{"learn":[7.498880302],"iteration":34,"passed_time":0.1899968073,"remaining_time":5.238483401},
{"learn":[7.401158744],"iteration":35,"passed_time":0.1919027008,"remaining_time":5.138727877},
{"learn":[7.306431077],"iteration":36,"passed_time":0.1940188514,"remaining_time":5.04973389},
{"learn":[7.223863468],"iteration":37,"passed_time":0.1954486345,"remaining_time":4.947936485},
{"learn":[7.143477682],"iteration":38,"passed_time":0.196824331,"remaining_time":4.849953387},
{"learn":[7.062817131],"iteration":39,"passed_time":0.1982743738,"remaining_time":4.75858497},
{"learn":[6.990793435],"iteration":40,"passed_time":0.1993075797,"remaining_time":4.661852902},
{"learn":[6.931862224],"iteration":41,"passed_time":0.2004096989,"remaining_time":4.571249799},
{"learn":[6.858296558],"iteration":42,"passed_time":0.2014388498,"remaining_time":4.483185565},
{"learn":[6.786268161],"iteration":43,"passed_time":0.2025912562,"remaining_time":4.401755475},
{"learn":[6.717118549],"iteration":44,"passed_time":0.2037754342,"remaining_time":4.324567549},
{"learn":[6.652948106],"iteration":45,"passed_time":0.2059183982,"remaining_time":4.270568519},
{"learn":[6.589686076],"iteration":46,"passed_time":0.2074647614,"remaining_time":4.206679098},
{"learn":[6.531283097],"iteration":47,"passed_time":0.2092005806,"remaining_time":4.149144849},
{"learn":[6.471368031],"iteration":48,"passed_time":0.2102905356,"remaining_time":4.081353048},
{"learn":[6.416481395],"iteration":49,"passed_time":0.2114954735,"remaining_time":4.018413997},
{"learn":[6.369870822],"iteration":50,"passed_time":0.2125772048,"remaining_time":3.955603282},
{"learn":[6.325678067],"iteration":51,"passed_time":0.2140172129,"remaining_time":3.901698419},
{"learn":[6.275766122],"iteration":52,"passed_time":0.2151338979,"remaining_time":3.843996251},
{"learn":[6.224773967],"iteration":53,"passed_time":0.2162821621,"remaining_time":3.788943061},
{"learn":[6.182249254],"iteration":54,"passed_time":0.2174046782,"remaining_time":3.735407652},
{"learn":[6.139904173],"iteration":55,"passed_time":0.2186094978,"remaining_time":3.685131534},
{"learn":[6.100525536],"iteration":56,"passed_time":0.2202408567,"remaining_time":3.643633822},
{"learn":[6.062568564],"iteration":57,"passed_time":0.2216585338,"remaining_time":3.600040324},
{"learn":[6.030559288],"iteration":58,"passed_time":0.2230587342,"remaining_time":3.557597778},
{"learn":[5.997931376],"iteration":59,"passed_time":0.224164034,"remaining_time":3.511903199},
{"learn":[5.964103835],"iteration":60,"passed_time":0.2252617039,"remaining_time":3.467553114},
{"learn":[5.933729724],"iteration":61,"passed_time":0.2262502163,"remaining_time":3.42294682},
{"learn":[5.901932711],"iteration":62,"passed_time":0.2272540989,"remaining_time":3.379953821},
{"learn":[5.873727795],"iteration":63,"passed_time":0.2282312085,"remaining_time":3.337881424},
{"learn":[5.846485734],"iteration":64,"passed_time":0.2291937238,"remaining_time":3.296863566},
{"learn":[5.820630862],"iteration":65,"passed_time":0.2302366569,"remaining_time":3.258197539},
{"learn":[5.793646238],"iteration":66,"passed_time":0.2312214621,"remaining_time":3.219845136},
{"learn":[5.765388646],"iteration":67,"passed_time":0.2322188199,"remaining_time":3.182763826},
{"learn":[5.747073912],"iteration":68,"passed_time":0.2334210321,"remaining_time":3.149492476},
{"learn":[5.722315217],"iteration":69,"passed_time":0.2350160299,"remaining_time":3.122355826},
{"learn":[5.699970599],"iteration":70,"passed_time":0.2366453033,"remaining_time":3.096387138},
{"learn":[5.682732647],"iteration":71,"passed_time":0.2378864869,"remaining_time":3.066092497},
{"learn":[5.663525791],"iteration":72,"passed_time":0.2388968986,"remaining_time":3.033663356},
{"learn":[5.642381613],"iteration":73,"passed_time":0.2400022135,"remaining_time":3.003270942},
{"learn":[5.621404779],"iteration":74,"passed_time":0.2413170363,"remaining_time":2.976243448},
{"learn":[5.602460129],"iteration":75,"passed_time":0.2424911523,"remaining_time":2.948181904},
{"learn":[5.587337574],"iteration":76,"passed_time":0.2437308035,"remaining_time":2.921604307},
{"learn":[5.572393026],"iteration":77,"passed_time":0.244766642,"remaining_time":2.89326723},
{"learn":[5.558425806],"iteration":78,"passed_time":0.2459083999,"remaining_time":2.866856155},
{"learn":[5.541518902],"iteration":79,"passed_time":0.2469474251,"remaining_time":2.839895388},
{"learn":[5.526157283],"iteration":80,"passed_time":0.2481657273,"remaining_time":2.815608684},
{"learn":[5.511746977],"iteration":81,"passed_time":0.2496504238,"remaining_time":2.794866939},
{"learn":[5.504975022],"iteration":82,"passed_time":0.2503023922,"remaining_time":2.76538908},
{"learn":[5.493980522],"iteration":83,"passed_time":0.2512260417,"remaining_time":2.739560169},
{"learn":[5.480745463],"iteration":84,"passed_time":0.2523071014,"remaining_time":2.716011739},
{"learn":[5.464052013],"iteration":85,"passed_time":0.2534411845,"remaining_time":2.693549333},
{"learn":[5.449143727],"iteration":86,"passed_time":0.2545225983,"remaining_time":2.671024508},
{"learn":[5.438255432],"iteration":87,"passed_time":0.2555008455,"remaining_time":2.647917853},
{"learn":[5.425927931],"iteration":88,"passed_time":0.2566313335,"remaining_time":2.626866796},
{"learn":[5.412331217],"iteration":89,"passed_time":0.2577465477,"remaining_time":2.606103983},
{"learn":[5.400691499],"iteration":90,"passed_time":0.258801169,"remaining_time":2.585167721},
{"learn":[5.391618744],"iteration":91,"passed_time":0.2597675226,"remaining_time":2.563792506},
{"learn":[5.380766572],"iteration":92,"passed_time":0.2608200092,"remaining_time":2.543696218},
{"learn":[5.372207183],"iteration":93,"passed_time":0.2618089522,"remaining_time":2.523392667},
{"learn":[5.362918837],"iteration":94,"passed_time":0.2632701971,"remaining_time":2.507995035},
{"learn":[5.348292324],"iteration":95,"passed_time":0.2645812346,"remaining_time":2.491473293},
{"learn":[5.339772295],"iteration":96,"passed_time":0.2656048876,"remaining_time":2.47258983},
{"learn":[5.331515983],"iteration":97,"passed_time":0.2665428152,"remaining_time":2.45328183},
{"learn":[5.323861644],"iteration":98,"passed_time":0.2676029348,"remaining_time":2.435457013},
{"learn":[5.313277281],"iteration":99,"passed_time":0.268628741,"remaining_time":2.417658669},
{"learn":[5.30685627],"iteration":100,"passed_time":0.2698596731,"remaining_time":2.402018279},
{"learn":[5.29652059],"iteration":101,"passed_time":0.271074041,"remaining_time":2.386514596},
{"learn":[5.288350766],"iteration":102,"passed_time":0.2722552988,"remaining_time":2.371000029},
{"learn":[5.27993346],"iteration":103,"passed_time":0.2731879556,"remaining_time":2.35361931},
{"learn":[5.271789139],"iteration":104,"passed_time":0.2742181784,"remaining_time":2.337383521},
{"learn":[5.262684686],"iteration":105,"passed_time":0.2751520632,"remaining_time":2.320622118},
{"learn":[5.251619772],"iteration":106,"passed_time":0.2761010661,"remaining_time":2.30428273},
{"learn":[5.241012171],"iteration":107,"passed_time":0.2770960891,"remaining_time":2.28860844},
{"learn":[5.232684032],"iteration":108,"passed_time":0.2783194709,"remaining_time":2.275070171},
{"learn":[5.224267141],"iteration":109,"passed_time":0.2793967468,"remaining_time":2.260573679},
{"learn":[5.216324968],"iteration":110,"passed_time":0.2803855393,"remaining_time":2.245610311},
{"learn":[5.211102527],"iteration":111,"passed_time":0.2815763866,"remaining_time":2.232498493},
{"learn":[5.206364257],"iteration":112,"passed_time":0.2825861027,"remaining_time":2.218175868},
{"learn":[5.196937641],"iteration":113,"passed_time":0.2837032741,"remaining_time":2.204921938},
{"learn":[5.190746047],"iteration":114,"passed_time":0.2848855962,"remaining_time":2.192380458},
{"learn":[5.181885213],"iteration":115,"passed_time":0.2859107664,"remaining_time":2.17883722},
{"learn":[5.178293568],"iteration":116,"passed_time":0.2866989527,"remaining_time":2.163719447},
{"learn":[5.170991438],"iteration":117,"passed_time":0.2876966466,"remaining_time":2.150410528},
{"learn":[5.166257212],"iteration":118,"passed_time":0.2886951582,"remaining_time":2.137314574},
{"learn":[5.161421246],"iteration":119,"passed_time":0.2896591438,"remaining_time":2.124167055},
{"learn":[5.158223542],"iteration":120,"passed_time":0.2907162926,"remaining_time":2.111897696},
{"learn":[5.15470988],"iteration":121,"passed_time":0.2915419047,"remaining_time":2.098145839},
{"learn":[5.146388143],"iteration":122,"passed_time":0.2929175804,"remaining_time":2.088526163},
{"learn":[5.139529364],"iteration":123,"passed_time":0.2942659728,"remaining_time":2.078846711},
{"learn":[5.134276023],"iteration":124,"passed_time":0.2952791562,"remaining_time":2.066954093},
{"learn":[5.128536065],"iteration":125,"passed_time":0.2962813674,"remaining_time":2.055158057},
{"learn":[5.123300353],"iteration":126,"passed_time":0.2971353943,"remaining_time":2.04251338},
{"learn":[5.116200518],"iteration":127,"passed_time":0.2981556496,"remaining_time":2.031185363},
{"learn":[5.108728704],"iteration":128,"passed_time":0.2991608422,"remaining_time":2.019915454},
{"learn":[5.104075866],"iteration":129,"passed_time":0.3001395995,"remaining_time":2.00862655},
{"learn":[5.100317606],"iteration":130,"passed_time":0.301160664,"remaining_time":1.997775702},
{"learn":[5.095814182],"iteration":131,"passed_time":0.3021661845,"remaining_time":1.986971577},
{"learn":[5.092146915],"iteration":132,"passed_time":0.3031847674,"remaining_time":1.97639995},
{"learn":[5.085258329],"iteration":133,"passed_time":0.3042265387,"remaining_time":1.966120765},
{"learn":[5.079219421],"iteration":134,"passed_time":0.3052258661,"remaining_time":1.955706475},
{"learn":[5.076476829],"iteration":135,"passed_time":0.3062994773,"remaining_time":1.945902562},
{"learn":[5.072133867],"iteration":136,"passed_time":0.3074021242,"remaining_time":1.936409001},
{"learn":[5.067031564],"iteration":137,"passed_time":0.3089566543,"remaining_time":1.929859681},
{"learn":[5.061358312],"iteration":138,"passed_time":0.3100176437,"remaining_time":1.920325117},
{"learn":[5.056759124],"iteration":139,"passed_time":0.3110434537,"remaining_time":1.910695501},
{"learn":[5.050254],"iteration":140,"passed_time":0.3121154034,"remaining_time":1.901469018},
{"learn":[5.048376474],"iteration":141,"passed_time":0.3127891941,"remaining_time":1.889951609},
{"learn":[5.042603751],"iteration":142,"passed_time":0.3137991264,"remaining_time":1.880600359},
{"learn":[5.037477349],"iteration":143,"passed_time":0.3148038983,"remaining_time":1.871334284},
{"learn":[5.03230489],"iteration":144,"passed_time":0.3157512619,"remaining_time":1.861843648},
{"learn":[5.025976187],"iteration":145,"passed_time":0.3167559628,"remaining_time":1.852805426},
{"learn":[5.01952451],"iteration":146,"passed_time":0.317682559,"remaining_time":1.843423285},
{"learn":[5.017569424],"iteration":147,"passed_time":0.3187069375,"remaining_time":1.834718316},
{"learn":[5.008962367],"iteration":148,"passed_time":0.3197336655,"remaining_time":1.826129862},
{"learn":[5.003880266],"iteration":149,"passed_time":0.3207527993,"remaining_time":1.817599196},
{"learn":[4.996387564],"iteration":150,"passed_time":0.3217796314,"remaining_time":1.809211305},
{"learn":[4.993361683],"iteration":151,"passed_time":0.3231950039,"remaining_time":1.803087916},
{"learn":[4.99005752],"iteration":152,"passed_time":0.3244232694,"remaining_time":1.795990256},
{"learn":[4.986908764],"iteration":153,"passed_time":0.32547784,"remaining_time":1.788014627},
{"learn":[4.985207175],"iteration":154,"passed_time":0.3267676331,"remaining_time":1.781410645},
{"learn":[4.979003494],"iteration":155,"passed_time":0.3283236297,"remaining_time":1.776315022},
{"learn":[4.973142217],"iteration":156,"passed_time":0.3296312643,"remaining_time":1.769930929},
{"learn":[4.967056696],"iteration":157,"passed_time":0.3306842079,"remaining_time":1.762253817},
{"learn":[4.961460696],"iteration":158,"passed_time":0.3317279801,"remaining_time":1.754611517},
{"learn":[4.954240363],"iteration":159,"passed_time":0.3329493673,"remaining_time":1.747984178},
{"learn":[4.952320707],"iteration":160,"passed_time":0.3335837511,"remaining_time":1.738365014},
{"learn":[4.948337777],"iteration":161,"passed_time":0.3345581103,"remaining_time":1.73061541},
{"learn":[4.943228639],"iteration":162,"passed_time":0.3355104665,"remaining_time":1.722835954},
{"learn":[4.938545759],"iteration":163,"passed_time":0.3365889643,"remaining_time":1.715782769},
{"learn":[4.935330572],"iteration":164,"passed_time":0.3381513953,"remaining_time":1.711251},
{"learn":[4.932051543],"iteration":165,"passed_time":0.3391531546,"remaining_time":1.703938138},
{"learn":[4.928964153],"iteration":166,"passed_time":0.3401695876,"remaining_time":1.696774051},
{"learn":[4.922860227],"iteration":167,"passed_time":0.341204492,"remaining_time":1.689774627},
{"learn":[4.917668772],"iteration":168,"passed_time":0.3423001162,"remaining_time":1.683144358},
{"learn":[4.910365386],"iteration":169,"passed_time":0.3433198746,"remaining_time":1.676208799},
{"learn":[4.906457206],"iteration":170,"passed_time":0.3442675856,"remaining_time":1.668993149},
{"learn":[4.901996508],"iteration":171,"passed_time":0.3452734478,"remaining_time":1.662130318},
{"learn":[4.896816173],"iteration":172,"passed_time":0.346228578,"remaining_time":1.655092682},
{"learn":[4.891123132],"iteration":173,"passed_time":0.3472705192,"remaining_time":1.648537062},
{"learn":[4.887630202],"iteration":174,"passed_time":0.3481986965,"remaining_time":1.641508141},
{"learn":[4.885259712],"iteration":175,"passed_time":0.3491984834,"remaining_time":1.634883809},
{"learn":[4.880659728],"iteration":176,"passed_time":0.3502111046,"remaining_time":1.628382707},
{"learn":[4.877299723],"iteration":177,"passed_time":0.3512316632,"remaining_time":1.621979928},
{"learn":[4.874038772],"iteration":178,"passed_time":0.3526190246,"remaining_time":1.617319661},
{"learn":[4.86943698],"iteration":179,"passed_time":0.3536800311,"remaining_time":1.611209031},
{"learn":[4.861268711],"iteration":180,"passed_time":0.3548259363,"remaining_time":1.605538352},
{"learn":[4.858673056],"iteration":181,"passed_time":0.355905433,"remaining_time":1.599618924},
{"learn":[4.854036207],"iteration":182,"passed_time":0.356901939,"remaining_time":1.593381881},
{"learn":[4.85130244],"iteration":183,"passed_time":0.3579966769,"remaining_time":1.587637437},
{"learn":[4.847510084],"iteration":184,"passed_time":0.3589991224,"remaining_time":1.581536674},
{"learn":[4.845691673],"iteration":185,"passed_time":0.3600666527,"remaining_time":1.575775566},
{"learn":[4.842058646],"iteration":186,"passed_time":0.3610558219,"remaining_time":1.569723974},
{"learn":[4.838623675],"iteration":187,"passed_time":0.36213062,"remaining_time":1.564096082},
{"learn":[4.834602161],"iteration":188,"passed_time":0.3632046055,"remaining_time":1.558512884},
{"learn":[4.830858976],"iteration":189,"passed_time":0.3642713158,"remaining_time":1.552946136},
{"learn":[4.827590511],"iteration":190,"passed_time":0.3652696371,"remaining_time":1.54713684},
{"learn":[4.822246226],"iteration":191,"passed_time":0.366579086,"remaining_time":1.542686987},
{"learn":[4.816686395],"iteration":192,"passed_time":0.3678897682,"remaining_time":1.538274834},
{"learn":[4.814797121],"iteration":193,"passed_time":0.3689670573,"remaining_time":1.532924991},
{"learn":[4.811639392],"iteration":194,"passed_time":0.370001841,"remaining_time":1.527443498},
{"learn":[4.804813432],"iteration":195,"passed_time":0.3710816212,"remaining_time":1.522191956},
{"learn":[4.80251613],"iteration":196,"passed_time":0.372065893,"remaining_time":1.516593462},
{"learn":[4.800087884],"iteration":197,"passed_time":0.3731024948,"remaining_time":1.51125354},
{"learn":[4.794773135],"iteration":198,"passed_time":0.3742656817,"remaining_time":1.506466387},
{"learn":[4.791664833],"iteration":199,"passed_time":0.375347581,"remaining_time":1.501390324},
{"learn":[4.785989873],"iteration":200,"passed_time":0.3764108806,"remaining_time":1.496280068},
{"learn":[4.782387142],"iteration":201,"passed_time":0.377376206,"remaining_time":1.490822834},
{"learn":[4.778623704],"iteration":202,"passed_time":0.3784498518,"remaining_time":1.485835132},
{"learn":[4.775772178],"iteration":203,"passed_time":0.3795955383,"remaining_time":1.481166904},
{"learn":[4.77023101],"iteration":204,"passed_time":0.3807740652,"remaining_time":1.476660399},
{"learn":[4.764496689],"iteration":205,"passed_time":0.3824164895,"remaining_time":1.473974236},
{"learn":[4.763138716],"iteration":206,"passed_time":0.3835620567,"remaining_time":1.469394739},
{"learn":[4.758053283],"iteration":207,"passed_time":0.3846081477,"remaining_time":1.464469485},
{"learn":[4.755063788],"iteration":208,"passed_time":0.3856635369,"remaining_time":1.459616544},
{"learn":[4.752465267],"iteration":209,"passed_time":0.386650649,"remaining_time":1.454542918},
{"learn":[4.748067377],"iteration":210,"passed_time":0.3876765144,"remaining_time":1.449652938},
{"learn":[4.744163298],"iteration":211,"passed_time":0.3888288237,"remaining_time":1.445269401},
{"learn":[4.736670896],"iteration":212,"passed_time":0.3901344584,"remaining_time":1.441482717},
{"learn":[4.73349255],"iteration":213,"passed_time":0.3912585058,"remaining_time":1.437052269},
{"learn":[4.731864595],"iteration":214,"passed_time":0.3923960875,"remaining_time":1.432701994},
{"learn":[4.728398311],"iteration":215,"passed_time":0.3934517872,"remaining_time":1.428084265},
{"learn":[4.723865975],"iteration":216,"passed_time":0.3947899911,"remaining_time":1.424518724},
{"learn":[4.723483365],"iteration":217,"passed_time":0.3986279204,"remaining_time":1.429940522},
{"learn":[4.72095416],"iteration":218,"passed_time":0.3997451629,"remaining_time":1.425575216},
{"learn":[4.716173382],"iteration":219,"passed_time":0.4009541171,"remaining_time":1.421564597},
{"learn":[4.710563974],"iteration":220,"passed_time":0.4022369268,"remaining_time":1.417839665},
{"learn":[4.707160263],"iteration":221,"passed_time":0.4033347477,"remaining_time":1.41348844},
{"learn":[4.70408351],"iteration":222,"passed_time":0.4044496032,"remaining_time":1.409225748},
{"learn":[4.702501831],"iteration":223,"passed_time":0.4055937532,"remaining_time":1.405092645},
{"learn":[4.700269738],"iteration":224,"passed_time":0.4067297902,"remaining_time":1.400958166},
{"learn":[4.695346302],"iteration":225,"passed_time":0.4078411813,"remaining_time":1.396765816},
{"learn":[4.689769299],"iteration":226,"passed_time":0.4089582492,"remaining_time":1.392619941},
{"learn":[4.687919514],"iteration":227,"passed_time":0.4099697895,"remaining_time":1.388143322},
{"learn":[4.682982074],"iteration":228,"passed_time":0.4114827076,"remaining_time":1.385385011},
{"learn":[4.679578702],"iteration":229,"passed_time":0.4127978532,"remaining_time":1.381975422},
{"learn":[4.675751423],"iteration":230,"passed_time":0.4137941823,"remaining_time":1.377522624},
{"learn":[4.672710726],"iteration":231,"passed_time":0.414909741,"remaining_time":1.373494315},
{"learn":[4.6690533],"iteration":232,"passed_time":0.4158959507,"remaining_time":1.369065211},
{"learn":[4.667595702],"iteration":233,"passed_time":0.416881001,"remaining_time":1.364661738},
{"learn":[4.664241291],"iteration":234,"passed_time":0.4179691534,"remaining_time":1.360622989},
{"learn":[4.662246999],"iteration":235,"passed_time":0.4190037024,"remaining_time":1.356435715},
{"learn":[4.658668443],"iteration":236,"passed_time":0.4200350363,"remaining_time":1.352264695},
{"learn":[4.658017572],"iteration":237,"passed_time":0.4210356982,"remaining_time":1.348021857},
{"learn":[4.657656705],"iteration":238,"passed_time":0.4220019956,"remaining_time":1.343696731},
{"learn":[4.653242871],"iteration":239,"passed_time":0.4230732416,"remaining_time":1.339731932},
{"learn":[4.6507302],"iteration":240,"passed_time":0.4244728051,"remaining_time":1.336825142},
{"learn":[4.647671336],"iteration":241,"passed_time":0.4264899152,"remaining_time":1.335865106},
{"learn":[4.645506007],"iteration":242,"passed_time":0.4280884012,"remaining_time":1.333592262},
{"learn":[4.641297906],"iteration":243,"passed_time":0.4292208157,"remaining_time":1.329880888},
{"learn":[4.63798107],"iteration":244,"passed_time":0.4303758195,"remaining_time":1.326260178},
{"learn":[4.635062318],"iteration":245,"passed_time":0.4317108547,"remaining_time":1.323211319},
{"learn":[4.631606017],"iteration":246,"passed_time":0.4327969955,"remaining_time":1.319417561},
{"learn":[4.630215494],"iteration":247,"passed_time":0.4338451691,"remaining_time":1.315530513},
{"learn":[4.62729814],"iteration":248,"passed_time":0.4349521265,"remaining_time":1.311843562},
{"learn":[4.624691756],"iteration":249,"passed_time":0.4360401658,"remaining_time":1.308120498},
{"learn":[4.621840053],"iteration":250,"passed_time":0.4372399281,"remaining_time":1.304751817},
{"learn":[4.619602091],"iteration":251,"passed_time":0.4384356609,"remaining_time":1.30138839},
{"learn":[4.613584029],"iteration":252,"passed_time":0.4396724993,"remaining_time":1.298163466},
{"learn":[4.6119388],"iteration":253,"passed_time":0.4413384353,"remaining_time":1.29621446},
{"learn":[4.60870702],"iteration":254,"passed_time":0.4427046105,"remaining_time":1.293391901},
{"learn":[4.604771557],"iteration":255,"passed_time":0.4438923879,"remaining_time":1.290062252},
{"learn":[4.604231277],"iteration":256,"passed_time":0.4450663666,"remaining_time":1.286709379},
{"learn":[4.600750354],"iteration":257,"passed_time":0.4461377305,"remaining_time":1.283078279},
{"learn":[4.596488253],"iteration":258,"passed_time":0.4472588231,"remaining_time":1.27960922},
{"learn":[4.59470784],"iteration":259,"passed_time":0.4490327525,"remaining_time":1.278016296},
{"learn":[4.588818005],"iteration":260,"passed_time":0.4508514205,"remaining_time":1.276548658},
{"learn":[4.585054174],"iteration":261,"passed_time":0.4523057606,"remaining_time":1.274052104},
{"learn":[4.581471435],"iteration":262,"passed_time":0.4536149507,"remaining_time":1.271156725},
{"learn":[4.577555199],"iteration":263,"passed_time":0.4547538516,"remaining_time":1.267798617},
{"learn":[4.57457145],"iteration":264,"passed_time":0.4565050899,"remaining_time":1.266155627},
{"learn":[4.573029224],"iteration":265,"passed_time":0.4577923627,"remaining_time":1.263231557},
{"learn":[4.571326203],"iteration":266,"passed_time":0.4589080142,"remaining_time":1.259848593},
{"learn":[4.571019224],"iteration":267,"passed_time":0.4601739009,"remaining_time":1.256892894},
{"learn":[4.565766631],"iteration":268,"passed_time":0.4614660024,"remaining_time":1.254020995},
{"learn":[4.563383471],"iteration":269,"passed_time":0.4627044498,"remaining_time":1.251015735},
{"learn":[4.558165805],"iteration":270,"passed_time":0.4638948205,"remaining_time":1.247894185},
{"learn":[4.55629209],"iteration":271,"passed_time":0.4649663126,"remaining_time":1.24446866},
{"learn":[4.549383848],"iteration":272,"passed_time":0.4660495985,"remaining_time":1.241091788},
{"learn":[4.546227503],"iteration":273,"passed_time":0.4673173933,"remaining_time":1.238220538},
{"learn":[4.540620977],"iteration":274,"passed_time":0.4684642156,"remaining_time":1.235042023},
{"learn":[4.532898237],"iteration":275,"passed_time":0.4695404319,"remaining_time":1.231693017},
{"learn":[4.529757367],"iteration":276,"passed_time":0.4714027278,"remaining_time":1.230412174},
{"learn":[4.52579294],"iteration":277,"passed_time":0.4727097268,"remaining_time":1.227684974},
{"learn":[4.521572155],"iteration":278,"passed_time":0.4740009226,"remaining_time":1.224927115},
{"learn":[4.518818099],"iteration":279,"passed_time":0.4750603508,"remaining_time":1.221583759},
{"learn":[4.514012334],"iteration":280,"passed_time":0.4761432903,"remaining_time":1.218316817},
{"learn":[4.508331416],"iteration":281,"passed_time":0.4771229704,"remaining_time":1.214802456},
{"learn":[4.506038537],"iteration":282,"passed_time":0.4782789666,"remaining_time":1.211752717},
{"learn":[4.505805643],"iteration":283,"passed_time":0.4793303656,"remaining_time":1.208452612},
{"learn":[4.501550352],"iteration":284,"passed_time":0.4809017269,"remaining_time":1.206472753},
{"learn":[4.494692643],"iteration":285,"passed_time":0.4821428636,"remaining_time":1.203671345},
{"learn":[4.489330245],"iteration":286,"passed_time":0.4835866347,"remaining_time":1.201384218},
{"learn":[4.484826955],"iteration":287,"passed_time":0.484920917,"remaining_time":1.198832267},
{"learn":[4.478285428],"iteration":288,"passed_time":0.4869710287,"remaining_time":1.198049832},
{"learn":[4.475311671],"iteration":289,"passed_time":0.4882104481,"remaining_time":1.195273856},
{"learn":[4.471581298],"iteration":290,"passed_time":0.4892407196,"remaining_time":1.191998867},
{"learn":[4.469164956],"iteration":291,"passed_time":0.4903355853,"remaining_time":1.188895871},
{"learn":[4.462068024],"iteration":292,"passed_time":0.4915358567,"remaining_time":1.186060924},
{"learn":[4.458540976],"iteration":293,"passed_time":0.4928920734,"remaining_time":1.183611578},
{"learn":[4.455757458],"iteration":294,"passed_time":0.4940885534,"remaining_time":1.180787899},
{"learn":[4.453027414],"iteration":295,"passed_time":0.4951596386,"remaining_time":1.177676978},
{"learn":[4.450659338],"iteration":296,"passed_time":0.4962239245,"remaining_time":1.1745637},
{"learn":[4.444696901],"iteration":297,"passed_time":0.4973121938,"remaining_time":1.171520671},
{"learn":[4.442052813],"iteration":298,"passed_time":0.4985336989,"remaining_time":1.168803087},
{"learn":[4.440036756],"iteration":299,"passed_time":0.4998894707,"remaining_time":1.166408765},
{"learn":[4.435017051],"iteration":300,"passed_time":0.5019645919,"remaining_time":1.16569186},
{"learn":[4.429962125],"iteration":301,"passed_time":0.5034384894,"remaining_time":1.163576376},
{"learn":[4.427666256],"iteration":302,"passed_time":0.5044791907,"remaining_time":1.160468633},
{"learn":[4.425030004],"iteration":303,"passed_time":0.50593283,"remaining_time":1.1583199},
{"learn":[4.422588771],"iteration":304,"passed_time":0.5071567328,"remaining_time":1.155652227},
{"learn":[4.418936667],"iteration":305,"passed_time":0.5082658198,"remaining_time":1.152733591},
{"learn":[4.416887976],"iteration":306,"passed_time":0.5094333593,"remaining_time":1.149958691},
{"learn":[4.413773354],"iteration":307,"passed_time":0.5106057551,"remaining_time":1.147205138},
{"learn":[4.411129391],"iteration":308,"passed_time":0.5120066602,"remaining_time":1.144972823},
{"learn":[4.40850819],"iteration":309,"passed_time":0.5131710381,"remaining_time":1.142219407},
{"learn":[4.404880292],"iteration":310,"passed_time":0.5141323098,"remaining_time":1.139026243},
{"learn":[4.404593827],"iteration":311,"passed_time":0.5153883138,"remaining_time":1.136497307},
{"learn":[4.402139942],"iteration":312,"passed_time":0.516741844,"remaining_time":1.134190565},
{"learn":[4.400284725],"iteration":313,"passed_time":0.5180157178,"remaining_time":1.131715868},
{"learn":[4.395805521],"iteration":314,"passed_time":0.5194258252,"remaining_time":1.129545048},
{"learn":[4.392838833],"iteration":315,"passed_time":0.5204941553,"remaining_time":1.126639248},
{"learn":[4.389213061],"iteration":316,"passed_time":0.5215693319,"remaining_time":1.123759791},
{"learn":[4.3861981],"iteration":317,"passed_time":0.5227079357,"remaining_time":1.121027711},
{"learn":[4.385054234],"iteration":318,"passed_time":0.5241042685,"remaining_time":1.118855821},
{"learn":[4.379364607],"iteration":319,"passed_time":0.5261608663,"remaining_time":1.118091841},
{"learn":[4.378387619],"iteration":320,"passed_time":0.5276342745,"remaining_time":1.116086207},
{"learn":[4.375816727],"iteration":321,"passed_time":0.5291181201,"remaining_time":1.114105855},
{"learn":[4.374600202],"iteration":322,"passed_time":0.5318578727,"remaining_time":1.114760928},
{"learn":[4.37098897],"iteration":323,"passed_time":0.5334452137,"remaining_time":1.112990631},
{"learn":[4.367418484],"iteration":324,"passed_time":0.5347211868,"remaining_time":1.110574773},
{"learn":[4.363584638],"iteration":325,"passed_time":0.5362305737,"remaining_time":1.108648487},
{"learn":[4.360770706],"iteration":326,"passed_time":0.5378694928,"remaining_time":1.106991342},
{"learn":[4.358675808],"iteration":327,"passed_time":0.5395793941,"remaining_time":1.105479734},
{"learn":[4.354228195],"iteration":328,"passed_time":0.5414405415,"remaining_time":1.10427539},
{"learn":[4.353773425],"iteration":329,"passed_time":0.5435531808,"remaining_time":1.10357767},
{"learn":[4.351648009],"iteration":330,"passed_time":0.5453216629,"remaining_time":1.102175808},
{"learn":[4.348209927],"iteration":331,"passed_time":0.5470620421,"remaining_time":1.100715193},
{"learn":[4.345852733],"iteration":332,"passed_time":0.5487359197,"remaining_time":1.099119695},
{"learn":[4.34237339],"iteration":333,"passed_time":0.550839043,"remaining_time":1.098379649},
{"learn":[4.340814362],"iteration":334,"passed_time":0.5523215877,"remaining_time":1.09639957},
{"learn":[4.339707068],"iteration":335,"passed_time":0.5536253797,"remaining_time":1.094069203},
{"learn":[4.335430786],"iteration":336,"passed_time":0.555069864,"remaining_time":1.09202172},
{"learn":[4.33521887],"iteration":337,"passed_time":0.5563494032,"remaining_time":1.089654748},
{"learn":[4.328507238],"iteration":338,"passed_time":0.5575941237,"remaining_time":1.0872263},
{"learn":[4.326140732],"iteration":339,"passed_time":0.5589809068,"remaining_time":1.085080584},
{"learn":[4.323785636],"iteration":340,"passed_time":0.5616002443,"remaining_time":1.085321293},
{"learn":[4.320632534],"iteration":341,"passed_time":0.5634429407,"remaining_time":1.084051038},
{"learn":[4.31973724],"iteration":342,"passed_time":0.5652379347,"remaining_time":1.082686073},
{"learn":[4.318000924],"iteration":343,"passed_time":0.5677631214,"remaining_time":1.082711069},
{"learn":[4.312713628],"iteration":344,"passed_time":0.5692222709,"remaining_time":1.080697355},
{"learn":[4.308220789],"iteration":345,"passed_time":0.5705669835,"remaining_time":1.078470541},
{"learn":[4.305890947],"iteration":346,"passed_time":0.5718040302,"remaining_time":1.076046201},
{"learn":[4.305137856],"iteration":347,"passed_time":0.5731456091,"remaining_time":1.073824532},
{"learn":[4.304787172],"iteration":348,"passed_time":0.5752151656,"remaining_time":1.072965825},
{"learn":[4.30350134],"iteration":349,"passed_time":0.5777221953,"remaining_time":1.072912648},
{"learn":[4.30293809],"iteration":350,"passed_time":0.5791431423,"remaining_time":1.07083732},
{"learn":[4.299548459],"iteration":351,"passed_time":0.5811439494,"remaining_time":1.06983318},
{"learn":[4.294768408],"iteration":352,"passed_time":0.5826316806,"remaining_time":1.067882995},
{"learn":[4.294581479],"iteration":353,"passed_time":0.5837242133,"remaining_time":1.065214242},
{"learn":[4.292551604],"iteration":354,"passed_time":0.5849385011,"remaining_time":1.062775587},
{"learn":[4.288628894],"iteration":355,"passed_time":0.5865238466,"remaining_time":1.061015048},
{"learn":[4.287802767],"iteration":356,"passed_time":0.5881735387,"remaining_time":1.059371388},
{"learn":[4.284566905],"iteration":357,"passed_time":0.5901328346,"remaining_time":1.058282904},
{"learn":[4.27890232],"iteration":358,"passed_time":0.5924501895,"remaining_time":1.05782889},
{"learn":[4.276938023],"iteration":359,"passed_time":0.5941606293,"remaining_time":1.056285563},
{"learn":[4.273425094],"iteration":360,"passed_time":0.5960247343,"remaining_time":1.055013311},
{"learn":[4.269726505],"iteration":361,"passed_time":0.5975073197,"remaining_time":1.053065387},
{"learn":[4.265565857],"iteration":362,"passed_time":0.5991036691,"remaining_time":1.051319662},
{"learn":[4.262117173],"iteration":363,"passed_time":0.6003131854,"remaining_time":1.048898862},
{"learn":[4.259185148],"iteration":364,"passed_time":0.6023295691,"remaining_time":1.047888428},
{"learn":[4.257668507],"iteration":365,"passed_time":0.6038016622,"remaining_time":1.045929655},
{"learn":[4.253432436],"iteration":366,"passed_time":0.6061158234,"remaining_time":1.04542593},
{"learn":[4.250216667],"iteration":367,"passed_time":0.6092956073,"remaining_time":1.046398978},
{"learn":[4.24514828],"iteration":368,"passed_time":0.6115197343,"remaining_time":1.045715318},
{"learn":[4.244015772],"iteration":369,"passed_time":0.6131977384,"remaining_time":1.044093447},
{"learn":[4.240329192],"iteration":370,"passed_time":0.6144569428,"remaining_time":1.041761232},
{"learn":[4.236718014],"iteration":371,"passed_time":0.6158128538,"remaining_time":1.039598044},
{"learn":[4.233495944],"iteration":372,"passed_time":0.6171900248,"remaining_time":1.037474921},
{"learn":[4.230357491],"iteration":373,"passed_time":0.6194985187,"remaining_time":1.036914633},
{"learn":[4.227381215],"iteration":374,"passed_time":0.6218576403,"remaining_time":1.036429401},
{"learn":[4.226169067],"iteration":375,"passed_time":0.6233568946,"remaining_time":1.034507187},
{"learn":[4.225963861],"iteration":376,"passed_time":0.625081303,"remaining_time":1.032959288},
{"learn":[4.224346548],"iteration":377,"passed_time":0.6267935813,"remaining_time":1.031390496},
{"learn":[4.222595381],"iteration":378,"passed_time":0.6280804612,"remaining_time":1.029123922},
{"learn":[4.219700938],"iteration":379,"passed_time":0.6294119221,"remaining_time":1.026935241},
{"learn":[4.216356207],"iteration":380,"passed_time":0.6307693029,"remaining_time":1.024793172},
{"learn":[4.214326494],"iteration":381,"passed_time":0.6319986919,"remaining_time":1.022448145},
{"learn":[4.212901398],"iteration":382,"passed_time":0.6332369088,"remaining_time":1.020123166},
{"learn":[4.211331091],"iteration":383,"passed_time":0.6349191147,"remaining_time":1.01851608},
{"learn":[4.208624791],"iteration":384,"passed_time":0.6366877056,"remaining_time":1.017046595},
{"learn":[4.204659106],"iteration":385,"passed_time":0.6381172071,"remaining_time":1.015036179},
{"learn":[4.202968852],"iteration":386,"passed_time":0.6404125269,"remaining_time":1.014400204},
{"learn":[4.197261935],"iteration":387,"passed_time":0.6421121516,"remaining_time":1.012816074},
{"learn":[4.196934403],"iteration":388,"passed_time":0.6432545956,"remaining_time":1.01035619},
{"learn":[4.192479929],"iteration":389,"passed_time":0.644429322,"remaining_time":1.007953555},
{"learn":[4.190243116],"iteration":390,"passed_time":0.6457947827,"remaining_time":1.005854278},
{"learn":[4.185852431],"iteration":391,"passed_time":0.6469942648,"remaining_time":1.003501309},
{"learn":[4.180967944],"iteration":392,"passed_time":0.6483820502,"remaining_time":1.00144505},
{"learn":[4.178283162],"iteration":393,"passed_time":0.6503124567,"remaining_time":1.000226774},
{"learn":[4.176341157],"iteration":394,"passed_time":0.6522457878,"remaining_time":0.9990093711},
{"learn":[4.176041504],"iteration":395,"passed_time":0.6534282561,"remaining_time":0.9966430977},
{"learn":[4.175564513],"iteration":396,"passed_time":0.6554792992,"remaining_time":0.9956020589},
{"learn":[4.170830274],"iteration":397,"passed_time":0.6571234266,"remaining_time":0.9939404593},
{"learn":[4.167804808],"iteration":398,"passed_time":0.6582570701,"remaining_time":0.9915100228},
{"learn":[4.165860548],"iteration":399,"passed_time":0.6594389095,"remaining_time":0.9891583642},
{"learn":[4.160950571],"iteration":400,"passed_time":0.6606862203,"remaining_time":0.9869103391},
{"learn":[4.158544115],"iteration":401,"passed_time":0.6619090963,"remaining_time":0.9846309442},
{"learn":[4.154448767],"iteration":402,"passed_time":0.6630087093,"remaining_time":0.9821741921},
{"learn":[4.15197457],"iteration":403,"passed_time":0.6647807656,"remaining_time":0.980716179},
{"learn":[4.149562679],"iteration":404,"passed_time":0.6666097381,"remaining_time":0.9793402325},
{"learn":[4.149327961],"iteration":405,"passed_time":0.6680829215,"remaining_time":0.9774415156},
{"learn":[4.147444889],"iteration":406,"passed_time":0.6692066802,"remaining_time":0.9750357773},
{"learn":[4.147254809],"iteration":407,"passed_time":0.670309267,"remaining_time":0.972605603},
{"learn":[4.144589165],"iteration":408,"passed_time":0.671484043,"remaining_time":0.9702862333},
{"learn":[4.141691034],"iteration":409,"passed_time":0.6726636914,"remaining_time":0.9679794584},
{"learn":[4.138893468],"iteration":410,"passed_time":0.6738300611,"remaining_time":0.9656591387},
{"learn":[4.136964597],"iteration":411,"passed_time":0.6749934069,"remaining_time":0.9633401051},
{"learn":[4.133773523],"iteration":412,"passed_time":0.6760938329,"remaining_time":0.9609372396},
{"learn":[4.131363444],"iteration":413,"passed_time":0.6771280966,"remaining_time":0.9584470159},
{"learn":[4.130228592],"iteration":414,"passed_time":0.6781491629,"remaining_time":0.9559452056},
{"learn":[4.12884186],"iteration":415,"passed_time":0.6797263108,"remaining_time":0.954231167},
{"learn":[4.12413494],"iteration":416,"passed_time":0.6813215949,"remaining_time":0.952543141},
{"learn":[4.119422508],"iteration":417,"passed_time":0.6828590705,"remaining_time":0.9507750694},
{"learn":[4.117038244],"iteration":418,"passed_time":0.684166096,"remaining_time":0.9486885484},
{"learn":[4.116067631],"iteration":419,"passed_time":0.68536376,"remaining_time":0.9464547162},
{"learn":[4.110343455],"iteration":420,"passed_time":0.6864031136,"remaining_time":0.9440080827},
{"learn":[4.105604544],"iteration":421,"passed_time":0.6875100436,"remaining_time":0.9416606759},
{"learn":[4.103390131],"iteration":422,"passed_time":0.6885815414,"remaining_time":0.9392708024},
{"learn":[4.096724402],"iteration":423,"passed_time":0.6896304722,"remaining_time":0.9368564905},
{"learn":[4.093431279],"iteration":424,"passed_time":0.6907523191,"remaining_time":0.9345472553},
{"learn":[4.091412744],"iteration":425,"passed_time":0.6919380375,"remaining_time":0.9323296562},
{"learn":[4.091192901],"iteration":426,"passed_time":0.6933642047,"remaining_time":0.9304395534},
{"learn":[4.088994581],"iteration":427,"passed_time":0.6957457501,"remaining_time":0.9298284324},
{"learn":[4.087845355],"iteration":428,"passed_time":0.6974077375,"remaining_time":0.9282513242},
{"learn":[4.083650279],"iteration":429,"passed_time":0.6987549014,"remaining_time":0.9262564972},
{"learn":[4.079840652],"iteration":430,"passed_time":0.6999521916,"remaining_time":0.9240668144},
{"learn":[4.075707828],"iteration":431,"passed_time":0.7011382966,"remaining_time":0.9218670196},
{"learn":[4.071345409],"iteration":432,"passed_time":0.7023174131,"remaining_time":0.9196627557},
{"learn":[4.067460475],"iteration":433,"passed_time":0.7033792742,"remaining_time":0.9173102977},
{"learn":[4.064914749],"iteration":434,"passed_time":0.7044741601,"remaining_time":0.9150066678},
{"learn":[4.063823175],"iteration":435,"passed_time":0.7056480466,"remaining_time":0.9128107758},
{"learn":[4.058898471],"iteration":436,"passed_time":0.7068401989,"remaining_time":0.9106430938},
{"learn":[4.054120355],"iteration":437,"passed_time":0.7083710655,"remaining_time":0.9089144721},
{"learn":[4.052715901],"iteration":438,"passed_time":0.7100164327,"remaining_time":0.9073330724},
{"learn":[4.052114167],"iteration":439,"passed_time":0.7112340763,"remaining_time":0.9052070061},
{"learn":[4.051377267],"iteration":440,"passed_time":0.7124111361,"remaining_time":0.903033617},
{"learn":[4.049275336],"iteration":441,"passed_time":0.7137047812,"remaining_time":0.9010119184},
{"learn":[4.047099198],"iteration":442,"passed_time":0.7148579158,"remaining_time":0.8988168378},
{"learn":[4.044348685],"iteration":443,"passed_time":0.7159663332,"remaining_time":0.8965704532},
{"learn":[4.042822379],"iteration":444,"passed_time":0.7170693576,"remaining_time":0.8943224573},
{"learn":[4.041258611],"iteration":445,"passed_time":0.7185425325,"remaining_time":0.892539379},
{"learn":[4.040044254],"iteration":446,"passed_time":0.7196960182,"remaining_time":0.8903621881},
{"learn":[4.036860137],"iteration":447,"passed_time":0.7208710896,"remaining_time":0.888216164},
{"learn":[4.036372284],"iteration":448,"passed_time":0.7219062136,"remaining_time":0.8859027253},
{"learn":[4.03368231],"iteration":449,"passed_time":0.7232935239,"remaining_time":0.8840254181},
{"learn":[4.032439519],"iteration":450,"passed_time":0.7247555293,"remaining_time":0.8822412097},
{"learn":[4.032008634],"iteration":451,"passed_time":0.7262015605,"remaining_time":0.8804390601},
{"learn":[4.030034932],"iteration":452,"passed_time":0.7275355309,"remaining_time":0.8785031687},
{"learn":[4.028173412],"iteration":453,"passed_time":0.7288556279,"remaining_time":0.8765532441},
{"learn":[4.023806097],"iteration":454,"passed_time":0.7299969319,"remaining_time":0.8743919294},
{"learn":[4.020239186],"iteration":455,"passed_time":0.7312860435,"remaining_time":0.8724114204},
{"learn":[4.017384838],"iteration":456,"passed_time":0.7324254944,"remaining_time":0.8702561126},
{"learn":[4.016468229],"iteration":457,"passed_time":0.7335665826,"remaining_time":0.8681071786},
{"learn":[4.014530169],"iteration":458,"passed_time":0.7347308531,"remaining_time":0.8659899598},
{"learn":[4.012884822],"iteration":459,"passed_time":0.7358600454,"remaining_time":0.8638357055},
{"learn":[4.008924707],"iteration":460,"passed_time":0.7369992535,"remaining_time":0.8616976088},
{"learn":[4.008286778],"iteration":461,"passed_time":0.7386887182,"remaining_time":0.8602046112},
{"learn":[4.006444202],"iteration":462,"passed_time":0.740067677,"remaining_time":0.8583506319},
{"learn":[4.003284363],"iteration":463,"passed_time":0.7414265201,"remaining_time":0.8564754629},
{"learn":[3.999811484],"iteration":464,"passed_time":0.7424619469,"remaining_time":0.8542304121},
{"learn":[3.997483319],"iteration":465,"passed_time":0.7435822389,"remaining_time":0.8520878016},
{"learn":[3.99708333],"iteration":466,"passed_time":0.7445995478,"remaining_time":0.8498320321},
{"learn":[3.995860263],"iteration":467,"passed_time":0.7457561478,"remaining_time":0.8477398946},
{"learn":[3.994131111],"iteration":468,"passed_time":0.7470657037,"remaining_time":0.8458249226},
{"learn":[3.993125499],"iteration":469,"passed_time":0.7483059082,"remaining_time":0.843834322},
{"learn":[3.992954084],"iteration":470,"passed_time":0.7494081693,"remaining_time":0.8416919779},
{"learn":[3.990635743],"iteration":471,"passed_time":0.7504649802,"remaining_time":0.8395031982},
{"learn":[3.986678254],"iteration":472,"passed_time":0.7515304624,"remaining_time":0.8373288661},
{"learn":[3.986393291],"iteration":473,"passed_time":0.7531252553,"remaining_time":0.8357465913},
{"learn":[3.986152671],"iteration":474,"passed_time":0.7549385389,"remaining_time":0.8344057536},
{"learn":[3.985596662],"iteration":475,"passed_time":0.7564795561,"remaining_time":0.8327632088},
{"learn":[3.983853457],"iteration":476,"passed_time":0.7582214284,"remaining_time":0.8313413146},
{"learn":[3.983263928],"iteration":477,"passed_time":0.7595971958,"remaining_time":0.8295182766},
{"learn":[3.980067202],"iteration":478,"passed_time":0.7609738965,"remaining_time":0.8276981212},
{"learn":[3.978115407],"iteration":479,"passed_time":0.7622262708,"remaining_time":0.8257451267},
{"learn":[3.972661644],"iteration":480,"passed_time":0.7634454102,"remaining_time":0.8237591848},
{"learn":[3.969938254],"iteration":481,"passed_time":0.764689877,"remaining_time":0.8218036437},
{"learn":[3.968211434],"iteration":482,"passed_time":0.7659415898,"remaining_time":0.8198588031},
{"learn":[3.966113368],"iteration":483,"passed_time":0.7674095327,"remaining_time":0.818147353},
{"learn":[3.962246044],"iteration":484,"passed_time":0.7690885987,"remaining_time":0.8166610894},
{"learn":[3.961319703],"iteration":485,"passed_time":0.7705863987,"remaining_time":0.8149823229},
{"learn":[3.96078191],"iteration":486,"passed_time":0.7719835682,"remaining_time":0.8131982967},
{"learn":[3.958913633],"iteration":487,"passed_time":0.7730912937,"remaining_time":0.811112177},
{"learn":[3.957428286],"iteration":488,"passed_time":0.7742922348,"remaining_time":0.8091274682},
{"learn":[3.952641965],"iteration":489,"passed_time":0.7753431483,"remaining_time":0.8069898074},
{"learn":[3.951486786],"iteration":490,"passed_time":0.7764106365,"remaining_time":0.8048737556},
{"learn":[3.94938344],"iteration":491,"passed_time":0.7776174148,"remaining_time":0.802905786},
{"learn":[3.947297924],"iteration":492,"passed_time":0.7787481564,"remaining_time":0.8008627086},
{"learn":[3.946284886],"iteration":493,"passed_time":0.7798528538,"remaining_time":0.7987966478},
{"learn":[3.943288204],"iteration":494,"passed_time":0.7809598793,"remaining_time":0.7967368466},
{"learn":[3.943076488],"iteration":495,"passed_time":0.7820534814,"remaining_time":0.7946672473},
{"learn":[3.942347078],"iteration":496,"passed_time":0.7842189893,"remaining_time":0.7936864218},
{"learn":[3.940251541],"iteration":497,"passed_time":0.7857459328,"remaining_time":0.7920571451},
{"learn":[3.939011019],"iteration":498,"passed_time":0.7870169806,"remaining_time":0.7901713572},
{"learn":[3.938760512],"iteration":499,"passed_time":0.7880845,"remaining_time":0.7880845},
{"learn":[3.934522727],"iteration":500,"passed_time":0.7891972005,"remaining_time":0.7860467126},
{"learn":[3.930091193],"iteration":501,"passed_time":0.7903982211,"remaining_time":0.7841002273},
{"learn":[3.927671752],"iteration":502,"passed_time":0.7916064578,"remaining_time":0.7821638361},
{"learn":[3.927280041],"iteration":503,"passed_time":0.7928117332,"remaining_time":0.7802274199},
{"learn":[3.925987561],"iteration":504,"passed_time":0.7939533476,"remaining_time":0.7782314991},
{"learn":[3.921645957],"iteration":505,"passed_time":0.7950146389,"remaining_time":0.7761605368},
{"learn":[3.920333743],"iteration":506,"passed_time":0.7964675523,"remaining_time":0.7744743654},
{"learn":[3.918659461],"iteration":507,"passed_time":0.7986702839,"remaining_time":0.7735153143},
{"learn":[3.916124385],"iteration":508,"passed_time":0.8002194954,"remaining_time":0.7719209671},
{"learn":[3.913849268],"iteration":509,"passed_time":0.8013259512,"remaining_time":0.7699014041},
{"learn":[3.912826119],"iteration":510,"passed_time":0.80245206,"remaining_time":0.7679042218},
{"learn":[3.910034145],"iteration":511,"passed_time":0.803647586,"remaining_time":0.7659766054},
{"learn":[3.90792379],"iteration":512,"passed_time":0.8048637209,"remaining_time":0.7640714076},
{"learn":[3.907823851],"iteration":513,"passed_time":0.8059014618,"remaining_time":0.7620002148},
{"learn":[3.904527401],"iteration":514,"passed_time":0.8069741947,"remaining_time":0.7599659892},
{"learn":[3.903378283],"iteration":515,"passed_time":0.8080644672,"remaining_time":0.7579519421},
{"learn":[3.902170135],"iteration":516,"passed_time":0.8092205226,"remaining_time":0.7560029253},
{"learn":[3.899435429],"iteration":517,"passed_time":0.810465456,"remaining_time":0.7541396714},
{"learn":[3.897497505],"iteration":518,"passed_time":0.8116478509,"remaining_time":0.7522208406},
{"learn":[3.896426119],"iteration":519,"passed_time":0.8132217198,"remaining_time":0.7506662029},
{"learn":[3.896044669],"iteration":520,"passed_time":0.8145528518,"remaining_time":0.7488883225},
{"learn":[3.892795942],"iteration":521,"passed_time":0.8158832873,"remaining_time":0.7471115159},
{"learn":[3.892413888],"iteration":522,"passed_time":0.8172159895,"remaining_time":0.7453384837},
{"learn":[3.891738985],"iteration":523,"passed_time":0.8183987554,"remaining_time":0.7434309305},
{"learn":[3.88822057],"iteration":524,"passed_time":0.819743133,"remaining_time":0.7416723584},
{"learn":[3.883837053],"iteration":525,"passed_time":0.8208550981,"remaining_time":0.7397059249},
{"learn":[3.881769742],"iteration":526,"passed_time":0.8218883443,"remaining_time":0.7376720813},
{"learn":[3.880356898],"iteration":527,"passed_time":0.8229756923,"remaining_time":0.7356903916},
{"learn":[3.879250273],"iteration":528,"passed_time":0.8243215643,"remaining_time":0.7339422623},
{"learn":[3.877174493],"iteration":529,"passed_time":0.8256639245,"remaining_time":0.7321925368},
{"learn":[3.875854201],"iteration":530,"passed_time":0.8267388485,"remaining_time":0.7302081355},
{"learn":[3.873189396],"iteration":531,"passed_time":0.8281284785,"remaining_time":0.7285039999},
{"learn":[3.871583368],"iteration":532,"passed_time":0.8295292644,"remaining_time":0.7268108189},
{"learn":[3.869622679],"iteration":533,"passed_time":0.8306299308,"remaining_time":0.724856831},
{"learn":[3.866860164],"iteration":534,"passed_time":0.8317587615,"remaining_time":0.7229305124},
{"learn":[3.864498444],"iteration":535,"passed_time":0.8327490021,"remaining_time":0.7208871959},
{"learn":[3.861416322],"iteration":536,"passed_time":0.8337924974,"remaining_time":0.7188937175},
{"learn":[3.860265769],"iteration":537,"passed_time":0.8348097581,"remaining_time":0.7168812421},
{"learn":[3.859328725],"iteration":538,"passed_time":0.8358895023,"remaining_time":0.7149259009},
{"learn":[3.858521278],"iteration":539,"passed_time":0.837043166,"remaining_time":0.713036771},
{"learn":[3.85599111],"iteration":540,"passed_time":0.8380829834,"remaining_time":0.7110537696},
{"learn":[3.852379816],"iteration":541,"passed_time":0.839180924,"remaining_time":0.7091233638},
{"learn":[3.851327537],"iteration":542,"passed_time":0.8402149302,"remaining_time":0.7071422157},
{"learn":[3.847854898],"iteration":543,"passed_time":0.8412265823,"remaining_time":0.7051458116},
{"learn":[3.847083414],"iteration":544,"passed_time":0.8427482474,"remaining_time":0.7035788121},
{"learn":[3.845397429],"iteration":545,"passed_time":0.8441570218,"remaining_time":0.7019181097},
{"learn":[3.841933528],"iteration":546,"passed_time":0.8452396091,"remaining_time":0.6999881955},
{"learn":[3.840996474],"iteration":547,"passed_time":0.8464247422,"remaining_time":0.6981459552},
{"learn":[3.838355966],"iteration":548,"passed_time":0.8477000645,"remaining_time":0.6963801987},
{"learn":[3.83342799],"iteration":549,"passed_time":0.848872032,"remaining_time":0.6945316626},
{"learn":[3.828161535],"iteration":550,"passed_time":0.8501236071,"remaining_time":0.692750453},
{"learn":[3.823502399],"iteration":551,"passed_time":0.8513173263,"remaining_time":0.6909242069},
{"learn":[3.820068862],"iteration":552,"passed_time":0.8525610293,"remaining_time":0.6891406512},
{"learn":[3.817951642],"iteration":553,"passed_time":0.8536337045,"remaining_time":0.6872213578},
{"learn":[3.815785958],"iteration":554,"passed_time":0.8546445815,"remaining_time":0.6852555653},
{"learn":[3.81503012],"iteration":555,"passed_time":0.855704384,"remaining_time":0.6833322779},
{"learn":[3.813529315],"iteration":556,"passed_time":0.857428748,"remaining_time":0.681940638},
{"learn":[3.808881326],"iteration":557,"passed_time":0.8589546409,"remaining_time":0.6803905937},
{"learn":[3.808740434],"iteration":558,"passed_time":0.8601729058,"remaining_time":0.6785979453},
{"learn":[3.80714352],"iteration":559,"passed_time":0.8612307312,"remaining_time":0.6766812888},
{"learn":[3.80573346],"iteration":560,"passed_time":0.8622264886,"remaining_time":0.6747191239},
{"learn":[3.803370052],"iteration":561,"passed_time":0.8633389941,"remaining_time":0.6728513869},
{"learn":[3.803215211],"iteration":562,"passed_time":0.8643903771,"remaining_time":0.6709388895},
{"learn":[3.801309667],"iteration":563,"passed_time":0.8656276651,"remaining_time":0.6691731595},
{"learn":[3.800003847],"iteration":564,"passed_time":0.8667249735,"remaining_time":0.6673015283},
{"learn":[3.798026138],"iteration":565,"passed_time":0.8677515487,"remaining_time":0.665378396},
{"learn":[3.794745847],"iteration":566,"passed_time":0.8689037297,"remaining_time":0.6635543474},
{"learn":[3.794312041],"iteration":567,"passed_time":0.870091562,"remaining_time":0.6617597796},
{"learn":[3.792205926],"iteration":568,"passed_time":0.8712901659,"remaining_time":0.6599755035},
{"learn":[3.788991061],"iteration":569,"passed_time":0.8731715199,"remaining_time":0.6587083396},
{"learn":[3.787391572],"iteration":570,"passed_time":0.8746754941,"remaining_time":0.6571554938},
{"learn":[3.7826445],"iteration":571,"passed_time":0.8760419153,"remaining_time":0.6554998947},
{"learn":[3.781700331],"iteration":572,"passed_time":0.8774426832,"remaining_time":0.6538709},
{"learn":[3.780045374],"iteration":573,"passed_time":0.8789644482,"remaining_time":0.6523324999},
{"learn":[3.775462644],"iteration":574,"passed_time":0.8803077033,"remaining_time":0.6506622155},
{"learn":[3.773711943],"iteration":575,"passed_time":0.881505629,"remaining_time":0.648886088},
{"learn":[3.772415806],"iteration":576,"passed_time":0.8826795831,"remaining_time":0.6470943911},
{"learn":[3.770170875],"iteration":577,"passed_time":0.883895823,"remaining_time":0.6453357047},
{"learn":[3.765166479],"iteration":578,"passed_time":0.8853190643,"remaining_time":0.643729406},
{"learn":[3.763976102],"iteration":579,"passed_time":0.8866704404,"remaining_time":0.6420716982},
{"learn":[3.760761708],"iteration":580,"passed_time":0.8880192435,"remaining_time":0.6404131894},
{"learn":[3.758155662],"iteration":581,"passed_time":0.8892625925,"remaining_time":0.6386800063},
{"learn":[3.756844548],"iteration":582,"passed_time":0.8904447443,"remaining_time":0.6369047313},
{"learn":[3.753098923],"iteration":583,"passed_time":0.8917886581,"remaining_time":0.6352467154},
{"learn":[3.751618946],"iteration":584,"passed_time":0.8928824353,"remaining_time":0.6334123259},
{"learn":[3.751398464],"iteration":585,"passed_time":0.8939238659,"remaining_time":0.631543482},
{"learn":[3.749920103],"iteration":586,"passed_time":0.8950561593,"remaining_time":0.6297413863},
{"learn":[3.748237465],"iteration":587,"passed_time":0.8961452799,"remaining_time":0.6279113186},
{"learn":[3.746021536],"iteration":588,"passed_time":0.8972603725,"remaining_time":0.6261018898},
{"learn":[3.74417648],"iteration":589,"passed_time":0.8986581373,"remaining_time":0.624491248},
{"learn":[3.738788389],"iteration":590,"passed_time":0.89973539,"remaining_time":0.622659517},
{"learn":[3.736021611],"iteration":591,"passed_time":0.9007795052,"remaining_time":0.6208074968},
{"learn":[3.734546151],"iteration":592,"passed_time":0.9022522561,"remaining_time":0.6192523916},
{"learn":[3.733527479],"iteration":593,"passed_time":0.9036784096,"remaining_time":0.6176657143},
{"learn":[3.733026392],"iteration":594,"passed_time":0.9049028543,"remaining_time":0.615942279},
{"learn":[3.730314752],"iteration":595,"passed_time":0.9060849932,"remaining_time":0.614191841},
{"learn":[3.727342596],"iteration":596,"passed_time":0.9072564979,"remaining_time":0.6124361284},
{"learn":[3.725459604],"iteration":597,"passed_time":0.9083312737,"remaining_time":0.6106173446},
{"learn":[3.723158842],"iteration":598,"passed_time":0.9094085397,"remaining_time":0.6088027119},
{"learn":[3.722362756],"iteration":599,"passed_time":0.9107382469,"remaining_time":0.6071588312},
{"learn":[3.721443615],"iteration":600,"passed_time":0.9118571977,"remaining_time":0.6053760763},
{"learn":[3.720743486],"iteration":601,"passed_time":0.9129875721,"remaining_time":0.6036030792},
{"learn":[3.720215334],"iteration":602,"passed_time":0.9140892625,"remaining_time":0.6018133287},
{"learn":[3.719436563],"iteration":603,"passed_time":0.9151991918,"remaining_time":0.6000312582},
{"learn":[3.715046574],"iteration":604,"passed_time":0.9167344991,"remaining_time":0.5985291358},
{"learn":[3.71443396],"iteration":605,"passed_time":0.9181797183,"remaining_time":0.5969683317},
{"learn":[3.712938941],"iteration":606,"passed_time":0.9193359435,"remaining_time":0.5952208003},
{"learn":[3.712814764],"iteration":607,"passed_time":0.9202901632,"remaining_time":0.5933449737},
{"learn":[3.71235348],"iteration":608,"passed_time":0.9214343889,"remaining_time":0.5915941643},
{"learn":[3.711223749],"iteration":609,"passed_time":0.9225865406,"remaining_time":0.5898504112},
{"learn":[3.710755648],"iteration":610,"passed_time":0.9236956943,"remaining_time":0.5880812194},
{"learn":[3.708668039],"iteration":611,"passed_time":0.9247767328,"remaining_time":0.58629636},
{"learn":[3.705623591],"iteration":612,"passed_time":0.9258293627,"remaining_time":0.5844958619},
{"learn":[3.704045802],"iteration":613,"passed_time":0.9269125984,"remaining_time":0.5827170407},
{"learn":[3.699915209],"iteration":614,"passed_time":0.9279919153,"remaining_time":0.5809380283},
{"learn":[3.696182221],"iteration":615,"passed_time":0.9292865996,"remaining_time":0.5792955426},
{"learn":[3.694263278],"iteration":616,"passed_time":0.9305923678,"remaining_time":0.5776610646},
{"learn":[3.693810229],"iteration":617,"passed_time":0.9318659426,"remaining_time":0.5760077509},
{"learn":[3.690900932],"iteration":618,"passed_time":0.9332890026,"remaining_time":0.5744476736},
{"learn":[3.688020895],"iteration":619,"passed_time":0.9344327778,"remaining_time":0.5727168638},
{"learn":[3.685491894],"iteration":620,"passed_time":0.935887487,"remaining_time":0.5711777094},
{"learn":[3.684328128],"iteration":621,"passed_time":0.9370810444,"remaining_time":0.5694801202},
{"learn":[3.680640153],"iteration":622,"passed_time":0.9381645569,"remaining_time":0.5677175569},
{"learn":[3.678932783],"iteration":623,"passed_time":0.9392251232,"remaining_time":0.5659433435},
{"learn":[3.674167041],"iteration":624,"passed_time":0.9402804112,"remaining_time":0.5641682467},
{"learn":[3.672200976],"iteration":625,"passed_time":0.9415868154,"remaining_time":0.5625454776},
{"learn":[3.670606604],"iteration":626,"passed_time":0.9427297279,"remaining_time":0.560826457},
{"learn":[3.665506042],"iteration":627,"passed_time":0.9438017269,"remaining_time":0.559067265},
{"learn":[3.664214007],"iteration":628,"passed_time":0.9448519623,"remaining_time":0.5572974213},
{"learn":[3.66261643],"iteration":629,"passed_time":0.9460781272,"remaining_time":0.5556331858},
{"learn":[3.662118449],"iteration":630,"passed_time":0.9477205751,"remaining_time":0.5542137753},
{"learn":[3.660871366],"iteration":631,"passed_time":0.9491750738,"remaining_time":0.5526842202},
{"learn":[3.656695243],"iteration":632,"passed_time":0.9505666062,"remaining_time":0.5511183957},
{"learn":[3.654497801],"iteration":633,"passed_time":0.9518085691,"remaining_time":0.5494667765},
{"learn":[3.654189134],"iteration":634,"passed_time":0.9528545309,"remaining_time":0.5477037855},
{"learn":[3.653957699],"iteration":635,"passed_time":0.9542561581,"remaining_time":0.5461466062},
{"learn":[3.651920725],"iteration":636,"passed_time":0.9558822406,"remaining_time":0.5447178231},
{"learn":[3.65106705],"iteration":637,"passed_time":0.9569812403,"remaining_time":0.5429893558},
{"learn":[3.650612844],"iteration":638,"passed_time":0.9579024271,"remaining_time":0.541162404},
{"learn":[3.649884732],"iteration":639,"passed_time":0.9588574172,"remaining_time":0.5393572972},
{"learn":[3.646276182],"iteration":640,"passed_time":0.9598960364,"remaining_time":0.5376016803},
{"learn":[3.645808194],"iteration":641,"passed_time":0.9614941471,"remaining_time":0.5361602876},
{"learn":[3.645042989],"iteration":642,"passed_time":0.96345376,"remaining_time":0.5349191171},
{"learn":[3.639864499],"iteration":643,"passed_time":0.9650300892,"remaining_time":0.5334638381},
{"learn":[3.637318478],"iteration":644,"passed_time":0.9677672906,"remaining_time":0.5326471134},
{"learn":[3.636344905],"iteration":645,"passed_time":0.9691919681,"remaining_time":0.5311051961},
{"learn":[3.634754643],"iteration":646,"passed_time":0.9703181128,"remaining_time":0.5294007633},
{"learn":[3.630724975],"iteration":647,"passed_time":0.9714914796,"remaining_time":0.5277237667},
{"learn":[3.629408252],"iteration":648,"passed_time":0.9729915663,"remaining_time":0.5262250227},
{"learn":[3.62790646],"iteration":649,"passed_time":0.9743819251,"remaining_time":0.5246671904},
{"learn":[3.627388973],"iteration":650,"passed_time":0.975499981,"remaining_time":0.5229638915},
{"learn":[3.625163557],"iteration":651,"passed_time":0.977185376,"remaining_time":0.5215652007},
{"learn":[3.623701985],"iteration":652,"passed_time":0.9942368103,"remaining_time":0.5283310462},
{"learn":[3.622342639],"iteration":653,"passed_time":0.9959364526,"remaining_time":0.5269021599},
{"learn":[3.621130639],"iteration":654,"passed_time":0.9971946045,"remaining_time":0.5252399062},
{"learn":[3.619125665],"iteration":655,"passed_time":0.999191692,"remaining_time":0.5239663751},
{"learn":[3.618878783],"iteration":656,"passed_time":1.000525983,"remaining_time":0.5223446153},
{"learn":[3.616207429],"iteration":657,"passed_time":1.001768613,"remaining_time":0.5206760876},
{"learn":[3.61206486],"iteration":658,"passed_time":1.002840823,"remaining_time":0.5189206684},
{"learn":[3.611955873],"iteration":659,"passed_time":1.004166596,"remaining_time":0.5172979436},
{"learn":[3.610713743],"iteration":660,"passed_time":1.005776328,"remaining_time":0.5158217476},
{"learn":[3.610044025],"iteration":661,"passed_time":1.007025394,"remaining_time":0.514161002},
{"learn":[3.607342669],"iteration":662,"passed_time":1.008803231,"remaining_time":0.5127702697},
{"learn":[3.602510618],"iteration":663,"passed_time":1.010184812,"remaining_time":0.5111778568},
{"learn":[3.600492392],"iteration":664,"passed_time":1.011996831,"remaining_time":0.5098029146},
{"learn":[3.597171065],"iteration":665,"passed_time":1.014018214,"remaining_time":0.508531657},
{"learn":[3.594358798],"iteration":666,"passed_time":1.015464323,"remaining_time":0.5069709437},
{"learn":[3.593945251],"iteration":667,"passed_time":1.016941907,"remaining_time":0.505426217},
{"learn":[3.593607748],"iteration":668,"passed_time":1.018315025,"remaining_time":0.5038300051},
{"learn":[3.592238714],"iteration":669,"passed_time":1.019507223,"remaining_time":0.5021453487},
{"learn":[3.590144654],"iteration":670,"passed_time":1.020602892,"remaining_time":0.500414831},
{"learn":[3.587151536],"iteration":671,"passed_time":1.021706343,"remaining_time":0.4986900008},
{"learn":[3.586070865],"iteration":672,"passed_time":1.023540837,"remaining_time":0.4973222193},
{"learn":[3.585102746],"iteration":673,"passed_time":1.02615179,"remaining_time":0.4963286104},
{"learn":[3.584362847],"iteration":674,"passed_time":1.027344647,"remaining_time":0.4946474224},
{"learn":[3.581407561],"iteration":675,"passed_time":1.028639135,"remaining_time":0.4930163899},
{"learn":[3.57919422],"iteration":676,"passed_time":1.029949783,"remaining_time":0.4913940617},
{"learn":[3.577632204],"iteration":677,"passed_time":1.031284102,"remaining_time":0.489783895},
{"learn":[3.573911195],"iteration":678,"passed_time":1.032435077,"remaining_time":0.4880878639},
{"learn":[3.573408216],"iteration":679,"passed_time":1.033570145,"remaining_time":0.4863859508},
{"learn":[3.571076482],"iteration":680,"passed_time":1.03501839,"remaining_time":0.4848324031},
{"learn":[3.568177107],"iteration":681,"passed_time":1.037347406,"remaining_time":0.483689846},
{"learn":[3.564824621],"iteration":682,"passed_time":1.039935966,"remaining_time":0.482664277},
{"learn":[3.562475026],"iteration":683,"passed_time":1.041446074,"remaining_time":0.4811359056},
{"learn":[3.561226889],"iteration":684,"passed_time":1.043603469,"remaining_time":0.4799052446},
{"learn":[3.559383467],"iteration":685,"passed_time":1.045621758,"remaining_time":0.4786082101},
{"learn":[3.555209766],"iteration":686,"passed_time":1.047282078,"remaining_time":0.4771459832},
{"learn":[3.55345383],"iteration":687,"passed_time":1.048982613,"remaining_time":0.4757014175},
{"learn":[3.552300968],"iteration":688,"passed_time":1.050571333,"remaining_time":0.4742056379},
{"learn":[3.551253986],"iteration":689,"passed_time":1.057376478,"remaining_time":0.4750532004},
{"learn":[3.549807725],"iteration":690,"passed_time":1.064373365,"remaining_time":0.4759643559},
{"learn":[3.547992926],"iteration":691,"passed_time":1.066295109,"remaining_time":0.4745937769},
{"learn":[3.545438607],"iteration":692,"passed_time":1.076028593,"remaining_time":0.4766822196},
{"learn":[3.543313763],"iteration":693,"passed_time":1.078995573,"remaining_time":0.4757530912},
{"learn":[3.542962896],"iteration":694,"passed_time":1.081599248,"remaining_time":0.4746586628},
{"learn":[3.539800465],"iteration":695,"passed_time":1.083241754,"remaining_time":0.4731400764},
{"learn":[3.53953187],"iteration":696,"passed_time":1.085923215,"remaining_time":0.4720727891},
{"learn":[3.536332425],"iteration":697,"passed_time":1.089771945,"remaining_time":0.4715059131},
{"learn":[3.534993327],"iteration":698,"passed_time":1.094379859,"remaining_time":0.471256563},
{"learn":[3.531637011],"iteration":699,"passed_time":1.096681302,"remaining_time":0.4700062723},
{"learn":[3.531040284],"iteration":700,"passed_time":1.098237406,"remaining_time":0.4684350703},
{"learn":[3.529973872],"iteration":701,"passed_time":1.10354003,"remaining_time":0.4684543148},
{"learn":[3.527325183],"iteration":702,"passed_time":1.105529514,"remaining_time":0.4670586994},
{"learn":[3.527200815],"iteration":703,"passed_time":1.107768411,"remaining_time":0.4657662636},
{"learn":[3.523459911],"iteration":704,"passed_time":1.109774151,"remaining_time":0.4643735808},
{"learn":[3.522729934],"iteration":705,"passed_time":1.111654984,"remaining_time":0.4629271464},
{"learn":[3.522260582],"iteration":706,"passed_time":1.113821603,"remaining_time":0.4615979204},
{"learn":[3.518641591],"iteration":707,"passed_time":1.118720001,"remaining_time":0.4613929947},
{"learn":[3.516856405],"iteration":708,"passed_time":1.12440688,"remaining_time":0.4614984514},
{"learn":[3.515083413],"iteration":709,"passed_time":1.126312274,"remaining_time":0.4600430415},
{"learn":[3.514671214],"iteration":710,"passed_time":1.127954616,"remaining_time":0.4584794433},
{"learn":[3.512617621],"iteration":711,"passed_time":1.129369299,"remaining_time":0.4568235367},
{"learn":[3.510747971],"iteration":712,"passed_time":1.133874844,"remaining_time":0.4564124549},
{"learn":[3.508149266],"iteration":713,"passed_time":1.136310958,"remaining_time":0.455160972},
{"learn":[3.504557165],"iteration":714,"passed_time":1.137870409,"remaining_time":0.4535567366},
{"learn":[3.501367208],"iteration":715,"passed_time":1.139560622,"remaining_time":0.4520044926},
{"learn":[3.497593362],"iteration":716,"passed_time":1.141761303,"remaining_time":0.4506533456},
{"learn":[3.496291169],"iteration":717,"passed_time":1.143444527,"remaining_time":0.449096597},
{"learn":[3.49330374],"iteration":718,"passed_time":1.144863918,"remaining_time":0.4474363852},
{"learn":[3.490044385],"iteration":719,"passed_time":1.14746144,"remaining_time":0.4462350046},
{"learn":[3.488891789],"iteration":720,"passed_time":1.14992631,"remaining_time":0.4449784194},
{"learn":[3.486869081],"iteration":721,"passed_time":1.15167025,"remaining_time":0.4434408997},
{"learn":[3.486303638],"iteration":722,"passed_time":1.153147025,"remaining_time":0.4418004506},
{"learn":[3.486035862],"iteration":723,"passed_time":1.154698011,"remaining_time":0.4401887444},
{"learn":[3.482668951],"iteration":724,"passed_time":1.156252264,"remaining_time":0.4385784449},
{"learn":[3.47820549],"iteration":725,"passed_time":1.157967588,"remaining_time":0.4370290896},
{"learn":[3.474392283],"iteration":726,"passed_time":1.15948314,"remaining_time":0.4354042604},
{"learn":[3.472268163],"iteration":727,"passed_time":1.160922004,"remaining_time":0.4337510783},
{"learn":[3.471209164],"iteration":728,"passed_time":1.162516738,"remaining_time":0.4321564281},
{"learn":[3.470049971],"iteration":729,"passed_time":1.164531811,"remaining_time":0.4307172451},
{"learn":[3.469078654],"iteration":730,"passed_time":1.166385315,"remaining_time":0.429217031},
{"learn":[3.468643292],"iteration":731,"passed_time":1.16766995,"remaining_time":0.4275075774},
{"learn":[3.468134848],"iteration":732,"passed_time":1.169053583,"remaining_time":0.4258353432},
{"learn":[3.467820182],"iteration":733,"passed_time":1.170383453,"remaining_time":0.4241444121},
{"learn":[3.465776156],"iteration":734,"passed_time":1.171728862,"remaining_time":0.422460066},
{"learn":[3.463037608],"iteration":735,"passed_time":1.173059073,"remaining_time":0.4207711893},
{"learn":[3.45965637],"iteration":736,"passed_time":1.174328354,"remaining_time":0.4190615429},
{"learn":[3.457275091],"iteration":737,"passed_time":1.177167518,"remaining_time":0.4179104196},
{"learn":[3.455522955],"iteration":738,"passed_time":1.178766119,"remaining_time":0.4163165859},
{"learn":[3.451270508],"iteration":739,"passed_time":1.180353784,"remaining_time":0.4147188972},
{"learn":[3.450978947],"iteration":740,"passed_time":1.181636869,"remaining_time":0.4130147762},
{"learn":[3.450608492],"iteration":741,"passed_time":1.183503332,"remaining_time":0.4115146357},
{"learn":[3.448122004],"iteration":742,"passed_time":1.184820186,"remaining_time":0.4098234023},
{"learn":[3.445646714],"iteration":743,"passed_time":1.186079328,"remaining_time":0.4081133171},
{"learn":[3.44411263],"iteration":744,"passed_time":1.187266388,"remaining_time":0.4063797704},
{"learn":[3.443264164],"iteration":745,"passed_time":1.188455031,"remaining_time":0.4046482277},
{"learn":[3.439521363],"iteration":746,"passed_time":1.189559285,"remaining_time":0.4028895571},
{"learn":[3.436809225],"iteration":747,"passed_time":1.191387963,"remaining_time":0.4013766935},
{"learn":[3.435509465],"iteration":748,"passed_time":1.193279613,"remaining_time":0.3998840892},
{"learn":[3.434450277],"iteration":749,"passed_time":1.195289654,"remaining_time":0.3984298848},
{"learn":[3.431786753],"iteration":750,"passed_time":1.19687835,"remaining_time":0.3968344995},
{"learn":[3.430150302],"iteration":751,"passed_time":1.199537369,"remaining_time":0.3955921109},
{"learn":[3.42696281],"iteration":752,"passed_time":1.200959042,"remaining_time":0.3939400843},
{"learn":[3.426870334],"iteration":753,"passed_time":1.202119089,"remaining_time":0.3922033103},
{"learn":[3.425200309],"iteration":754,"passed_time":1.20330124,"remaining_time":0.3904752369},
{"learn":[3.423383783],"iteration":755,"passed_time":1.20447569,"remaining_time":0.3887461221},
{"learn":[3.422752979],"iteration":756,"passed_time":1.206155045,"remaining_time":0.3871805494},
{"learn":[3.420845924],"iteration":757,"passed_time":1.207782055,"remaining_time":0.3855979649},
{"learn":[3.418917862],"iteration":758,"passed_time":1.209420727,"remaining_time":0.384018966},
{"learn":[3.417095735],"iteration":759,"passed_time":1.21087913,"remaining_time":0.3823828832},
{"learn":[3.414391848],"iteration":760,"passed_time":1.21233968,"remaining_time":0.3807479415},
{"learn":[3.41426711],"iteration":761,"passed_time":1.213705062,"remaining_time":0.3790837331},
{"learn":[3.411976013],"iteration":762,"passed_time":1.215131476,"remaining_time":0.3774392657},
{"learn":[3.408614844],"iteration":763,"passed_time":1.216504231,"remaining_time":0.3757787939},
{"learn":[3.407906721],"iteration":764,"passed_time":1.217737711,"remaining_time":0.3740762902},
{"learn":[3.407494015],"iteration":765,"passed_time":1.218940155,"remaining_time":0.3723655304},
{"learn":[3.406287128],"iteration":766,"passed_time":1.222113845,"remaining_time":0.3712549229},
{"learn":[3.404600442],"iteration":767,"passed_time":1.223789537,"remaining_time":0.3696864226},
{"learn":[3.404012662],"iteration":768,"passed_time":1.225396396,"remaining_time":0.3680969669},
{"learn":[3.400398762],"iteration":769,"passed_time":1.226924342,"remaining_time":0.3664838943},
{"learn":[3.399737714],"iteration":770,"passed_time":1.228176266,"remaining_time":0.3647890596},
{"learn":[3.399185251],"iteration":771,"passed_time":1.229652233,"remaining_time":0.3631615405},
{"learn":[3.397245411],"iteration":772,"passed_time":1.231206406,"remaining_time":0.3615573792},
{"learn":[3.396229831],"iteration":773,"passed_time":1.232583379,"remaining_time":0.3599016067},
{"learn":[3.394002836],"iteration":774,"passed_time":1.233742772,"remaining_time":0.3581833854},
{"learn":[3.389617243],"iteration":775,"passed_time":1.235942353,"remaining_time":0.3567668649},
{"learn":[3.385426488],"iteration":776,"passed_time":1.237871138,"remaining_time":0.3552706097},
{"learn":[3.385072258],"iteration":777,"passed_time":1.239378981,"remaining_time":0.3536531282},
{"learn":[3.383842366],"iteration":778,"passed_time":1.24076452,"remaining_time":0.3520012311},
{"learn":[3.380110746],"iteration":779,"passed_time":1.241929038,"remaining_time":0.3502876775},
{"learn":[3.378595218],"iteration":780,"passed_time":1.243130664,"remaining_time":0.3485859352},
{"learn":[3.377371219],"iteration":781,"passed_time":1.244567242,"remaining_time":0.3469509704},
{"learn":[3.375814782],"iteration":782,"passed_time":1.245870726,"remaining_time":0.3452796265},
{"learn":[3.374195887],"iteration":783,"passed_time":1.24701721,"remaining_time":0.343565966},
{"learn":[3.373704309],"iteration":784,"passed_time":1.248302807,"remaining_time":0.3418918517},
{"learn":[3.372971757],"iteration":785,"passed_time":1.251140424,"remaining_time":0.3406412859},
{"learn":[3.371565136],"iteration":786,"passed_time":1.252890304,"remaining_time":0.3390922932},
{"learn":[3.3700309],"iteration":787,"passed_time":1.255127754,"remaining_time":0.3376739642},
{"learn":[3.368186663],"iteration":788,"passed_time":1.256751391,"remaining_time":0.3360894087},
{"learn":[3.366710398],"iteration":789,"passed_time":1.2581059,"remaining_time":0.334433214},
{"learn":[3.364598042],"iteration":790,"passed_time":1.259272868,"remaining_time":0.3327282293},
{"learn":[3.36348442],"iteration":791,"passed_time":1.260473587,"remaining_time":0.3310334673},
{"learn":[3.362001759],"iteration":792,"passed_time":1.261481696,"remaining_time":0.3292896734},
{"learn":[3.361580401],"iteration":793,"passed_time":1.262547564,"remaining_time":0.3275627181},
{"learn":[3.359543675],"iteration":794,"passed_time":1.263636431,"remaining_time":0.3258433564},
{"learn":[3.35766119],"iteration":795,"passed_time":1.265645218,"remaining_time":0.3243613373},
{"learn":[3.354592969],"iteration":796,"passed_time":1.267271016,"remaining_time":0.3227804469},
{"learn":[3.350985986],"iteration":797,"passed_time":1.268732265,"remaining_time":0.3211577914},
{"learn":[3.349589624],"iteration":798,"passed_time":1.270102404,"remaining_time":0.3195126197},
{"learn":[3.349110856],"iteration":799,"passed_time":1.271297771,"remaining_time":0.3178244428},
{"learn":[3.345315441],"iteration":800,"passed_time":1.272431401,"remaining_time":0.3161221584},
{"learn":[3.34397474],"iteration":801,"passed_time":1.273572288,"remaining_time":0.3144230837},
{"learn":[3.343800902],"iteration":802,"passed_time":1.274694574,"remaining_time":0.3127208358},
{"learn":[3.342329465],"iteration":803,"passed_time":1.276145975,"remaining_time":0.3111002627},
{"learn":[3.34220347],"iteration":804,"passed_time":1.277518904,"remaining_time":0.3094611011},
{"learn":[3.341279219],"iteration":805,"passed_time":1.279070942,"remaining_time":0.3078657106},
{"learn":[3.337329521],"iteration":806,"passed_time":1.281332026,"remaining_time":0.3064400014},
{"learn":[3.336708453],"iteration":807,"passed_time":1.283283797,"remaining_time":0.304938724},
{"learn":[3.333252703],"iteration":808,"passed_time":1.284768381,"remaining_time":0.3033260332},
{"learn":[3.332186769],"iteration":809,"passed_time":1.285968677,"remaining_time":0.3016469737},
{"learn":[3.330594851],"iteration":810,"passed_time":1.287196426,"remaining_time":0.2999754927},
{"learn":[3.327867442],"iteration":811,"passed_time":1.288265873,"remaining_time":0.2982684534},
{"learn":[3.327563111],"iteration":812,"passed_time":1.289357912,"remaining_time":0.2965681789},
{"learn":[3.326308994],"iteration":813,"passed_time":1.29046305,"remaining_time":0.2948723922},
{"learn":[3.326249879],"iteration":814,"passed_time":1.291632343,"remaining_time":0.2931926178},
{"learn":[3.322336238],"iteration":815,"passed_time":1.292775361,"remaining_time":0.2915081697},
{"learn":[3.320491154],"iteration":816,"passed_time":1.29452613,"remaining_time":0.2899611772},
{"learn":[3.320434271],"iteration":817,"passed_time":1.296362766,"remaining_time":0.2884327914},
{"learn":[3.319609638],"iteration":818,"passed_time":1.297838815,"remaining_time":0.2868239627},
{"learn":[3.316182682],"iteration":819,"passed_time":1.299256866,"remaining_time":0.2852027266},
{"learn":[3.313126612],"iteration":820,"passed_time":1.300382213,"remaining_time":0.2835181682},
{"learn":[3.311222803],"iteration":821,"passed_time":1.301500658,"remaining_time":0.2818334758},
{"learn":[3.309627335],"iteration":822,"passed_time":1.302687344,"remaining_time":0.2801648359},
{"learn":[3.307974895],"iteration":823,"passed_time":1.303716136,"remaining_time":0.2784636408},
{"learn":[3.307321505],"iteration":824,"passed_time":1.304915787,"remaining_time":0.2768003185},
{"learn":[3.306759087],"iteration":825,"passed_time":1.306103012,"remaining_time":0.2751355013},
{"learn":[3.30484037],"iteration":826,"passed_time":1.307259378,"remaining_time":0.2734653839},
{"learn":[3.30201994],"iteration":827,"passed_time":1.308421388,"remaining_time":0.2717976796},
{"learn":[3.299302297],"iteration":828,"passed_time":1.310288566,"remaining_time":0.2702766523},
{"learn":[3.298132671],"iteration":829,"passed_time":1.31195407,"remaining_time":0.2687134843},
{"learn":[3.296976183],"iteration":830,"passed_time":1.313444527,"remaining_time":0.2671144707},
{"learn":[3.293144745],"iteration":831,"passed_time":1.314702183,"remaining_time":0.26546871},
{"learn":[3.290284404],"iteration":832,"passed_time":1.315890551,"remaining_time":0.2638099904},
{"learn":[3.288285745],"iteration":833,"passed_time":1.316974961,"remaining_time":0.2621317069},
{"learn":[3.286662667],"iteration":834,"passed_time":1.318234379,"remaining_time":0.2604894282},
{"learn":[3.285692682],"iteration":835,"passed_time":1.319548719,"remaining_time":0.2588588396},
{"learn":[3.284565611],"iteration":836,"passed_time":1.320719129,"remaining_time":0.2572009774},
{"learn":[3.283897383],"iteration":837,"passed_time":1.321872265,"remaining_time":0.255540939},
{"learn":[3.280712855],"iteration":838,"passed_time":1.322902745,"remaining_time":0.2538585721},
{"learn":[3.280468341],"iteration":839,"passed_time":1.324406494,"remaining_time":0.2522679036},
{"learn":[3.277814895],"iteration":840,"passed_time":1.326486971,"remaining_time":0.2507864784},
{"learn":[3.276316385],"iteration":841,"passed_time":1.328084489,"remaining_time":0.2492130038},
{"learn":[3.27557063],"iteration":842,"passed_time":1.329378424,"remaining_time":0.2475829331},
{"learn":[3.27499628],"iteration":843,"passed_time":1.330515944,"remaining_time":0.2459247479},
{"learn":[3.273569958],"iteration":844,"passed_time":1.331673513,"remaining_time":0.2442714728},
{"learn":[3.269665595],"iteration":845,"passed_time":1.332985089,"remaining_time":0.2426474039},
{"learn":[3.267984685],"iteration":846,"passed_time":1.334370741,"remaining_time":0.2410374537},
{"learn":[3.267702508],"iteration":847,"passed_time":1.335669788,"remaining_time":0.2394125093},
{"learn":[3.266671924],"iteration":848,"passed_time":1.337007197,"remaining_time":0.2377951552},
{"learn":[3.265359825],"iteration":849,"passed_time":1.339283105,"remaining_time":0.2363440774},
{"learn":[3.2618983],"iteration":850,"passed_time":1.341306235,"remaining_time":0.2348468026},
{"learn":[3.260456253],"iteration":851,"passed_time":1.343750721,"remaining_time":0.2334214867},
{"learn":[3.258389147],"iteration":852,"passed_time":1.345297351,"remaining_time":0.231839051},
{"learn":[3.258108469],"iteration":853,"passed_time":1.346678306,"remaining_time":0.2302283756},
{"learn":[3.256424936],"iteration":854,"passed_time":1.348042678,"remaining_time":0.228615425},
{"learn":[3.254817983],"iteration":855,"passed_time":1.349384346,"remaining_time":0.2269992357},
{"learn":[3.253898449],"iteration":856,"passed_time":1.350667718,"remaining_time":0.2253739599},
{"learn":[3.253023652],"iteration":857,"passed_time":1.351986761,"remaining_time":0.2237553846},
{"learn":[3.252845542],"iteration":858,"passed_time":1.353490486,"remaining_time":0.2221678213},
{"learn":[3.252316026],"iteration":859,"passed_time":1.356146715,"remaining_time":0.22076807},
{"learn":[3.24975301],"iteration":860,"passed_time":1.357655946,"remaining_time":0.2191802282},
{"learn":[3.249151075],"iteration":861,"passed_time":1.359078442,"remaining_time":0.2175786833},
{"learn":[3.246257135],"iteration":862,"passed_time":1.360772494,"remaining_time":0.2160206624},
{"learn":[3.243826471],"iteration":863,"passed_time":1.362001037,"remaining_time":0.2143890522},
{"learn":[3.243190653],"iteration":864,"passed_time":1.363234329,"remaining_time":0.2127591149},
{"learn":[3.24008797],"iteration":865,"passed_time":1.364379448,"remaining_time":0.2111164503},
{"learn":[3.240036811],"iteration":866,"passed_time":1.365462399,"remaining_time":0.2094653969},
{"learn":[3.238676314],"iteration":867,"passed_time":1.366775399,"remaining_time":0.2078506368},
{"learn":[3.237848782],"iteration":868,"passed_time":1.368190643,"remaining_time":0.2062519842},
{"learn":[3.236405498],"iteration":869,"passed_time":1.370011173,"remaining_time":0.2047143133},
{"learn":[3.233378068],"iteration":870,"passed_time":1.371624055,"remaining_time":0.2031452389},
{"learn":[3.233169169],"iteration":871,"passed_time":1.372928628,"remaining_time":0.2015308077},
{"learn":[3.232434885],"iteration":872,"passed_time":1.374303343,"remaining_time":0.1999272905},
{"learn":[3.229978115],"iteration":873,"passed_time":1.375509312,"remaining_time":0.1982999695},
{"learn":[3.229648848],"iteration":874,"passed_time":1.376562659,"remaining_time":0.1966518085},
{"learn":[3.227208761],"iteration":875,"passed_time":1.377748597,"remaining_time":0.195023774},
{"learn":[3.226258869],"iteration":876,"passed_time":1.378996827,"remaining_time":0.1934054843},
{"learn":[3.225331995],"iteration":877,"passed_time":1.380126375,"remaining_time":0.1917715464},
{"learn":[3.221968268],"iteration":878,"passed_time":1.381323576,"remaining_time":0.1901480691},
{"learn":[3.221166317],"iteration":879,"passed_time":1.382536447,"remaining_time":0.1885276973},
{"learn":[3.220047503],"iteration":880,"passed_time":1.384941092,"remaining_time":0.1870692281},
{"learn":[3.21982781],"iteration":881,"passed_time":1.386835657,"remaining_time":0.1855403713},
{"learn":[3.216693405],"iteration":882,"passed_time":1.388163162,"remaining_time":0.1839355493},
{"learn":[3.214798761],"iteration":883,"passed_time":1.389219021,"remaining_time":0.1822957086},
{"learn":[3.214395085],"iteration":884,"passed_time":1.390217704,"remaining_time":0.1806497581},
{"learn":[3.213470696],"iteration":885,"passed_time":1.391379797,"remaining_time":0.1790262944},
{"learn":[3.211595017],"iteration":886,"passed_time":1.392923406,"remaining_time":0.1774524745},
{"learn":[3.210965255],"iteration":887,"passed_time":1.394157017,"remaining_time":0.1758396238},
{"learn":[3.209413583],"iteration":888,"passed_time":1.395361172,"remaining_time":0.1742239484},
{"learn":[3.208331683],"iteration":889,"passed_time":1.396420463,"remaining_time":0.1725912932},
{"learn":[3.207110711],"iteration":890,"passed_time":1.397743351,"remaining_time":0.170992172},
{"learn":[3.204519413],"iteration":891,"passed_time":1.39937152,"remaining_time":0.1694306325},
{"learn":[3.201421296],"iteration":892,"passed_time":1.400827463,"remaining_time":0.1678483075},
{"learn":[3.200691259],"iteration":893,"passed_time":1.402367571,"remaining_time":0.1662762444},
{"learn":[3.200485067],"iteration":894,"passed_time":1.403799894,"remaining_time":0.1646916077},
{"learn":[3.197467568],"iteration":895,"passed_time":1.405189788,"remaining_time":0.1631023862},
{"learn":[3.195838544],"iteration":896,"passed_time":1.406461502,"remaining_time":0.1615000387},
{"learn":[3.195671746],"iteration":897,"passed_time":1.407537209,"remaining_time":0.159876164},
{"learn":[3.194213094],"iteration":898,"passed_time":1.40865434,"remaining_time":0.1582581628},
{"learn":[3.192884691],"iteration":899,"passed_time":1.409857543,"remaining_time":0.1566508381},
{"learn":[3.188364239],"iteration":900,"passed_time":1.411220757,"remaining_time":0.1550619921},
{"learn":[3.185219478],"iteration":901,"passed_time":1.412881238,"remaining_time":0.1535059438},
{"learn":[3.184120387],"iteration":902,"passed_time":1.41507717,"remaining_time":0.1520071822},
{"learn":[3.183725321],"iteration":903,"passed_time":1.416981234,"remaining_time":0.1504758832},
{"learn":[3.181264554],"iteration":904,"passed_time":1.418600261,"remaining_time":0.1489138396},
{"learn":[3.180741589],"iteration":905,"passed_time":1.420051555,"remaining_time":0.1473342673},
{"learn":[3.179782639],"iteration":906,"passed_time":1.421163908,"remaining_time":0.1457202243},
{"learn":[3.176377564],"iteration":907,"passed_time":1.422233216,"remaining_time":0.144102925},
{"learn":[3.174078182],"iteration":908,"passed_time":1.423435479,"remaining_time":0.1425001415},
{"learn":[3.171242379],"iteration":909,"passed_time":1.424526789,"remaining_time":0.1408872649},
{"learn":[3.170421012],"iteration":910,"passed_time":1.425574297,"remaining_time":0.1392712541},
{"learn":[3.170087224],"iteration":911,"passed_time":1.426714952,"remaining_time":0.1376654778},
{"learn":[3.167303059],"iteration":912,"passed_time":1.428015461,"remaining_time":0.136075953},
{"learn":[3.16705966],"iteration":913,"passed_time":1.430054154,"remaining_time":0.1345565178},
{"learn":[3.165667683],"iteration":914,"passed_time":1.431620895,"remaining_time":0.132992105},
{"learn":[3.164689733],"iteration":915,"passed_time":1.433102354,"remaining_time":0.1314198665},
{"learn":[3.163311455],"iteration":916,"passed_time":1.434404084,"remaining_time":0.1298315583},
{"learn":[3.159425016],"iteration":917,"passed_time":1.436083271,"remaining_time":0.1282775906},
{"learn":[3.159327058],"iteration":918,"passed_time":1.43725346,"remaining_time":0.1266784878},
{"learn":[3.15819426],"iteration":919,"passed_time":1.438408758,"remaining_time":0.1250790225},
{"learn":[3.157086603],"iteration":920,"passed_time":1.439901358,"remaining_time":0.1235094542},
{"learn":[3.153354154],"iteration":921,"passed_time":1.441395592,"remaining_time":0.121940191},
{"learn":[3.153261317],"iteration":922,"passed_time":1.442890291,"remaining_time":0.1203711294},
{"learn":[3.153168454],"iteration":923,"passed_time":1.444583125,"remaining_time":0.1188185254},
{"learn":[3.152080399],"iteration":924,"passed_time":1.446054161,"remaining_time":0.1172476347},
{"learn":[3.151635144],"iteration":925,"passed_time":1.447868585,"remaining_time":0.115704401},
{"learn":[3.147762655],"iteration":926,"passed_time":1.449478166,"remaining_time":0.1141444511},
{"learn":[3.147172317],"iteration":927,"passed_time":1.45078549,"remaining_time":0.1125609432},
{"learn":[3.146254125],"iteration":928,"passed_time":1.452192403,"remaining_time":0.1109856411},
{"learn":[3.144869828],"iteration":929,"passed_time":1.454147057,"remaining_time":0.109451929},
{"learn":[3.143466218],"iteration":930,"passed_time":1.455466523,"remaining_time":0.1078702364},
{"learn":[3.141919643],"iteration":931,"passed_time":1.456773254,"remaining_time":0.1062881774},
{"learn":[3.141054135],"iteration":932,"passed_time":1.458641497,"remaining_time":0.1047470314},
{"learn":[3.139390417],"iteration":933,"passed_time":1.46042959,"remaining_time":0.1031995213},
{"learn":[3.139025283],"iteration":934,"passed_time":1.461875783,"remaining_time":0.1016277282},
{"learn":[3.137824183],"iteration":935,"passed_time":1.463534444,"remaining_time":0.1000707312},
{"learn":[3.135620453],"iteration":936,"passed_time":1.464770546,"remaining_time":0.09848510608},
{"learn":[3.13443178],"iteration":937,"passed_time":1.466251679,"remaining_time":0.09691642225},
{"learn":[3.132765713],"iteration":938,"passed_time":1.467544487,"remaining_time":0.09533569085},
{"learn":[3.131434124],"iteration":939,"passed_time":1.468820526,"remaining_time":0.09375450168},
{"learn":[3.128384262],"iteration":940,"passed_time":1.469996131,"remaining_time":0.09216766387},
{"learn":[3.128120455],"iteration":941,"passed_time":1.471046063,"remaining_time":0.0905739614},
{"learn":[3.126314615],"iteration":942,"passed_time":1.472644067,"remaining_time":0.08901454066},
{"learn":[3.125409666],"iteration":943,"passed_time":1.475077382,"remaining_time":0.08750459048},
{"learn":[3.123072589],"iteration":944,"passed_time":1.476669031,"remaining_time":0.0859437002},
{"learn":[3.122921099],"iteration":945,"passed_time":1.478515746,"remaining_time":0.08439730475},
{"learn":[3.122182662],"iteration":946,"passed_time":1.48000333,"remaining_time":0.08283017583},
{"learn":[3.120040951],"iteration":947,"passed_time":1.48124138,"remaining_time":0.08124952718},
{"learn":[3.118767799],"iteration":948,"passed_time":1.482594308,"remaining_time":0.07967577419},
{"learn":[3.118203218],"iteration":949,"passed_time":1.484022912,"remaining_time":0.07810646904},
{"learn":[3.116343362],"iteration":950,"passed_time":1.485537431,"remaining_time":0.07654188658},
{"learn":[3.11480829],"iteration":951,"passed_time":1.487381192,"remaining_time":0.0749940097},
{"learn":[3.112607903],"iteration":952,"passed_time":1.48917809,"remaining_time":0.07344320067},
{"learn":[3.111661241],"iteration":953,"passed_time":1.490832773,"remaining_time":0.0718850184},
{"learn":[3.110249676],"iteration":954,"passed_time":1.492547114,"remaining_time":0.07032944516},
{"learn":[3.107333579],"iteration":955,"passed_time":1.493999414,"remaining_time":0.0687614793},
{"learn":[3.107149851],"iteration":956,"passed_time":1.495316739,"remaining_time":0.06718769048},
{"learn":[3.106867336],"iteration":957,"passed_time":1.499937539,"remaining_time":0.06575926579},
{"learn":[3.10364681],"iteration":958,"passed_time":1.501399331,"remaining_time":0.06418912677},
{"learn":[3.102703811],"iteration":959,"passed_time":1.50432264,"remaining_time":0.06268010998},
{"learn":[3.101469264],"iteration":960,"passed_time":1.505926114,"remaining_time":0.06111458737},
{"learn":[3.09863569],"iteration":961,"passed_time":1.507722749,"remaining_time":0.05955661588},
{"learn":[3.09645939],"iteration":962,"passed_time":1.509683123,"remaining_time":0.05800443982},
{"learn":[3.096240186],"iteration":963,"passed_time":1.510947224,"remaining_time":0.05642541499},
{"learn":[3.094838828],"iteration":964,"passed_time":1.512196225,"remaining_time":0.0548464952},
{"learn":[3.094176802],"iteration":965,"passed_time":1.513441428,"remaining_time":0.0532681248},
{"learn":[3.093182279],"iteration":966,"passed_time":1.514571906,"remaining_time":0.05168652832},
{"learn":[3.090150687],"iteration":967,"passed_time":1.516892626,"remaining_time":0.05014521078},
{"learn":[3.088612829],"iteration":968,"passed_time":1.520067692,"remaining_time":0.04862961658},
{"learn":[3.087153684],"iteration":969,"passed_time":1.521741763,"remaining_time":0.04706417824},
{"learn":[3.085866843],"iteration":970,"passed_time":1.523833277,"remaining_time":0.04551098355},
{"learn":[3.082669094],"iteration":971,"passed_time":1.525589044,"remaining_time":0.04394700951},
{"learn":[3.081047548],"iteration":972,"passed_time":1.526967063,"remaining_time":0.04237215899},
{"learn":[3.079684322],"iteration":973,"passed_time":1.528384811,"remaining_time":0.04079877318},
{"learn":[3.07613431],"iteration":974,"passed_time":1.529721087,"remaining_time":0.03922361761},
{"learn":[3.074005935],"iteration":975,"passed_time":1.531530093,"remaining_time":0.03766057606},
{"learn":[3.072988853],"iteration":976,"passed_time":1.533851538,"remaining_time":0.03610909455},
{"learn":[3.072344268],"iteration":977,"passed_time":1.535334074,"remaining_time":0.03453716731},
{"learn":[3.070654438],"iteration":978,"passed_time":1.537005626,"remaining_time":0.03296947716},
{"learn":[3.069724506],"iteration":979,"passed_time":1.538453043,"remaining_time":0.03139700088},
{"learn":[3.067763166],"iteration":980,"passed_time":1.539755922,"remaining_time":0.02982198015},
{"learn":[3.066737893],"iteration":981,"passed_time":1.541070906,"remaining_time":0.02824773554},
{"learn":[3.065248174],"iteration":982,"passed_time":1.542283784,"remaining_time":0.02667225262},
{"learn":[3.063186837],"iteration":983,"passed_time":1.543431185,"remaining_time":0.02509644203},
{"learn":[3.062880371],"iteration":984,"passed_time":1.544556899,"remaining_time":0.02352117105},
{"learn":[3.061288645],"iteration":985,"passed_time":1.546035635,"remaining_time":0.02195182443},
{"learn":[3.059970575],"iteration":986,"passed_time":1.548252392,"remaining_time":0.02039238206},
{"learn":[3.059576341],"iteration":987,"passed_time":1.549903453,"remaining_time":0.01882473829},
{"learn":[3.058175919],"iteration":988,"passed_time":1.551820095,"remaining_time":0.01725987972},
{"learn":[3.056830702],"iteration":989,"passed_time":1.553736616,"remaining_time":0.01569430925},
{"learn":[3.056336579],"iteration":990,"passed_time":1.555075436,"remaining_time":0.01412278398},
{"learn":[3.055810414],"iteration":991,"passed_time":1.556325365,"remaining_time":0.01255101101},
{"learn":[3.055476518],"iteration":992,"passed_time":1.55759884,"remaining_time":0.01098005224},
{"learn":[3.053331734],"iteration":993,"passed_time":1.558864519,"remaining_time":0.009409644985},
{"learn":[3.050890374],"iteration":994,"passed_time":1.560465056,"remaining_time":0.007841532945},
{"learn":[3.04972623],"iteration":995,"passed_time":1.562774962,"remaining_time":0.006276204665},
{"learn":[3.047217327],"iteration":996,"passed_time":1.564826602,"remaining_time":0.004708605622},
{"learn":[3.047155483],"iteration":997,"passed_time":1.566131216,"remaining_time":0.003138539511},
{"learn":[3.04430671],"iteration":998,"passed_time":1.567303178,"remaining_time":0.00156887205},
{"learn":[3.042664195],"iteration":999,"passed_time":1.568633848,"remaining_time":0}
]}